{
  "ㄅㄚ": [
    {
      "char": "八",
      "freq": 950
    },
    {
      "char": "巴",
      "freq": 940
    },
    {
      "char": "吧",
      "freq": 930
    },
    {
      "char": "把",
      "freq": 920
    },
    {
      "char": "爸",
      "freq": 910
    },
    {
      "char": "拔",
      "freq": 900
    },
    {
      "char": "罷",
      "freq": 890
    },
    {
      "char": "霸",
      "freq": 880
    }
  ],
  "ㄅㄞ": [
    {
      "char": "百",
      "freq": 950
    },
    {
      "char": "白",
      "freq": 940
    },
    {
      "char": "拜",
      "freq": 930
    },
    {
      "char": "敗",
      "freq": 920
    },
    {
      "char": "擺",
      "freq": 910
    },
    {
      "char": "柏",
      "freq": 900
    }
  ],
  "ㄅㄢ": [
    {
      "char": "半",
      "freq": 950
    },
    {
      "char": "班",
      "freq": 940
    },
    {
      "char": "般",
      "freq": 930
    },
    {
      "char": "版",
      "freq": 920
    },
    {
      "char": "板",
      "freq": 910
    },
    {
      "char": "辦",
      "freq": 900
    },
    {
      "char": "伴",
      "freq": 890
    },
    {
      "char": "扮",
      "freq": 880
    }
  ],
  "ㄅㄤ": [
    {
      "char": "幫",
      "freq": 950
    },
    {
      "char": "棒",
      "freq": 940
    },
    {
      "char": "榜",
      "freq": 930
    },
    {
      "char": "膀",
      "freq": 920
    },
    {
      "char": "綁",
      "freq": 910
    },
    {
      "char": "傍",
      "freq": 900
    }
  ],
  "ㄅㄠ": [
    {
      "char": "包",
      "freq": 950
    },
    {
      "char": "報",
      "freq": 940
    },
    {
      "char": "保",
      "freq": 930
    },
    {
      "char": "寶",
      "freq": 920
    },
    {
      "char": "抱",
      "freq": 910
    },
    {
      "char": "暴",
      "freq": 900
    },
    {
      "char": "飽",
      "freq": 890
    },
    {
      "char": "薄",
      "freq": 880
    }
  ],
  "ㄅㄟ": [
    {
      "char": "北",
      "freq": 950
    },
    {
      "char": "背",
      "freq": 940
    },
    {
      "char": "被",
      "freq": 930
    },
    {
      "char": "杯",
      "freq": 920
    },
    {
      "char": "備",
      "freq": 910
    },
    {
      "char": "悲",
      "freq": 900
    },
    {
      "char": "倍",
      "freq": 890
    }
  ],
  "ㄅㄣ": [
    {
      "char": "本",
      "freq": 950
    },
    {
      "char": "笨",
      "freq": 940
    },
    {
      "char": "奔",
      "freq": 930
    },
    {
      "char": "賁",
      "freq": 920
    }
  ],
  "ㄅㄥ": [
    {
      "char": "崩",
      "freq": 950
    },
    {
      "char": "繃",
      "freq": 940
    },
    {
      "char": "蹦",
      "freq": 930
    },
    {
      "char": "迸",
      "freq": 920
    }
  ],
  "ㄅㄧ": [
    {
      "char": "比",
      "freq": 960
    },
    {
      "char": "必",
      "freq": 950
    },
    {
      "char": "筆",
      "freq": 940
    },
    {
      "char": "鼻",
      "freq": 930
    },
    {
      "char": "閉",
      "freq": 920
    },
    {
      "char": "避",
      "freq": 910
    },
    {
      "char": "幣",
      "freq": 900
    },
    {
      "char": "壁",
      "freq": 890
    }
  ],
  "ㄅㄧㄝ": [
    {
      "char": "別",
      "freq": 950
    },
    {
      "char": "憋",
      "freq": 920
    }
  ],
  "ㄅㄧㄠ": [
    {
      "char": "表",
      "freq": 960
    },
    {
      "char": "標",
      "freq": 950
    },
    {
      "char": "彪",
      "freq": 920
    },
    {
      "char": "鏢",
      "freq": 910
    }
  ],
  "ㄅㄧㄢ": [
    {
      "char": "邊",
      "freq": 960
    },
    {
      "char": "變",
      "freq": 950
    },
    {
      "char": "便",
      "freq": 940
    },
    {
      "char": "遍",
      "freq": 930
    },
    {
      "char": "編",
      "freq": 920
    },
    {
      "char": "辯",
      "freq": 910
    },
    {
      "char": "辨",
      "freq": 900
    }
  ],
  "ㄅㄧㄣ": [
    {
      "char": "賓",
      "freq": 950
    },
    {
      "char": "濱",
      "freq": 940
    },
    {
      "char": "彬",
      "freq": 930
    }
  ],
  "ㄅㄧㄥ": [
    {
      "char": "病",
      "freq": 960
    },
    {
      "char": "兵",
      "freq": 950
    },
    {
      "char": "冰",
      "freq": 940
    },
    {
      "char": "並",
      "freq": 930
    },
    {
      "char": "丙",
      "freq": 920
    },
    {
      "char": "餅",
      "freq": 910
    }
  ],
  "ㄅㄨ": [
    {
      "char": "不",
      "freq": 999
    },
    {
      "char": "部",
      "freq": 960
    },
    {
      "char": "步",
      "freq": 950
    },
    {
      "char": "布",
      "freq": 940
    },
    {
      "char": "補",
      "freq": 930
    },
    {
      "char": "卜",
      "freq": 920
    },
    {
      "char": "捕",
      "freq": 910
    }
  ],
  "ㄆㄚ": [
    {
      "char": "怕",
      "freq": 950
    },
    {
      "char": "爬",
      "freq": 940
    },
    {
      "char": "趴",
      "freq": 930
    },
    {
      "char": "啪",
      "freq": 920
    },
    {
      "char": "帕",
      "freq": 910
    }
  ],
  "ㄆㄞ": [
    {
      "char": "排",
      "freq": 950
    },
    {
      "char": "拍",
      "freq": 940
    },
    {
      "char": "派",
      "freq": 930
    },
    {
      "char": "牌",
      "freq": 920
    },
    {
      "char": "徘",
      "freq": 910
    }
  ],
  "ㄆㄢ": [
    {
      "char": "判",
      "freq": 950
    },
    {
      "char": "盤",
      "freq": 940
    },
    {
      "char": "盼",
      "freq": 930
    },
    {
      "char": "畔",
      "freq": 920
    },
    {
      "char": "叛",
      "freq": 910
    }
  ],
  "ㄆㄤ": [
    {
      "char": "旁",
      "freq": 950
    },
    {
      "char": "胖",
      "freq": 940
    },
    {
      "char": "龐",
      "freq": 930
    },
    {
      "char": "彷",
      "freq": 920
    }
  ],
  "ㄆㄠ": [
    {
      "char": "跑",
      "freq": 950
    },
    {
      "char": "泡",
      "freq": 940
    },
    {
      "char": "砲",
      "freq": 930
    },
    {
      "char": "拋",
      "freq": 920
    },
    {
      "char": "刨",
      "freq": 910
    }
  ],
  "ㄆㄟ": [
    {
      "char": "配",
      "freq": 950
    },
    {
      "char": "培",
      "freq": 940
    },
    {
      "char": "賠",
      "freq": 930
    },
    {
      "char": "佩",
      "freq": 920
    },
    {
      "char": "陪",
      "freq": 910
    }
  ],
  "ㄆㄣ": [
    {
      "char": "盆",
      "freq": 950
    },
    {
      "char": "噴",
      "freq": 940
    }
  ],
  "ㄆㄥ": [
    {
      "char": "朋",
      "freq": 960
    },
    {
      "char": "碰",
      "freq": 950
    },
    {
      "char": "捧",
      "freq": 940
    },
    {
      "char": "棚",
      "freq": 930
    },
    {
      "char": "膨",
      "freq": 920
    },
    {
      "char": "蓬",
      "freq": 910
    }
  ],
  "ㄆㄧ": [
    {
      "char": "皮",
      "freq": 960
    },
    {
      "char": "批",
      "freq": 950
    },
    {
      "char": "匹",
      "freq": 940
    },
    {
      "char": "劈",
      "freq": 930
    },
    {
      "char": "屁",
      "freq": 920
    },
    {
      "char": "脾",
      "freq": 910
    },
    {
      "char": "疲",
      "freq": 900
    }
  ],
  "ㄆㄧㄝ": [
    {
      "char": "片",
      "freq": 950
    },
    {
      "char": "偏",
      "freq": 940
    },
    {
      "char": "篇",
      "freq": 930
    },
    {
      "char": "騙",
      "freq": 920
    },
    {
      "char": "翩",
      "freq": 910
    }
  ],
  "ㄆㄧㄠ": [
    {
      "char": "票",
      "freq": 960
    },
    {
      "char": "漂",
      "freq": 950
    },
    {
      "char": "飄",
      "freq": 940
    },
    {
      "char": "瓢",
      "freq": 930
    }
  ],
  "ㄆㄧㄢ": [
    {
      "char": "片",
      "freq": 950
    },
    {
      "char": "偏",
      "freq": 940
    },
    {
      "char": "篇",
      "freq": 930
    },
    {
      "char": "騙",
      "freq": 920
    }
  ],
  "ㄆㄧㄣ": [
    {
      "char": "品",
      "freq": 960
    },
    {
      "char": "拼",
      "freq": 950
    },
    {
      "char": "貧",
      "freq": 940
    },
    {
      "char": "聘",
      "freq": 930
    },
    {
      "char": "頻",
      "freq": 920
    }
  ],
  "ㄆㄧㄥ": [
    {
      "char": "平",
      "freq": 960
    },
    {
      "char": "瓶",
      "freq": 950
    },
    {
      "char": "評",
      "freq": 940
    },
    {
      "char": "屏",
      "freq": 930
    },
    {
      "char": "蘋",
      "freq": 920
    },
    {
      "char": "憑",
      "freq": 910
    }
  ],
  "ㄆㄨ": [
    {
      "char": "鋪",
      "freq": 950
    },
    {
      "char": "普",
      "freq": 940
    },
    {
      "char": "僕",
      "freq": 930
    },
    {
      "char": "撲",
      "freq": 920
    },
    {
      "char": "樸",
      "freq": 910
    },
    {
      "char": "浦",
      "freq": 900
    }
  ],
  "ㄇㄚ": [
    {
      "char": "馬",
      "freq": 960
    },
    {
      "char": "嗎",
      "freq": 950
    },
    {
      "char": "媽",
      "freq": 940
    },
    {
      "char": "麻",
      "freq": 930
    },
    {
      "char": "罵",
      "freq": 920
    },
    {
      "char": "瑪",
      "freq": 910
    }
  ],
  "ㄇㄞ": [
    {
      "char": "買",
      "freq": 960
    },
    {
      "char": "賣",
      "freq": 950
    },
    {
      "char": "邁",
      "freq": 940
    },
    {
      "char": "埋",
      "freq": 930
    },
    {
      "char": "麥",
      "freq": 920
    }
  ],
  "ㄇㄢ": [
    {
      "char": "滿",
      "freq": 960
    },
    {
      "char": "慢",
      "freq": 950
    },
    {
      "char": "漫",
      "freq": 940
    },
    {
      "char": "蠻",
      "freq": 930
    },
    {
      "char": "饅",
      "freq": 920
    },
    {
      "char": "瞞",
      "freq": 910
    }
  ],
  "ㄇㄤ": [
    {
      "char": "忙",
      "freq": 960
    },
    {
      "char": "芒",
      "freq": 940
    },
    {
      "char": "盲",
      "freq": 930
    },
    {
      "char": "茫",
      "freq": 920
    }
  ],
  "ㄇㄠ": [
    {
      "char": "貓",
      "freq": 960
    },
    {
      "char": "毛",
      "freq": 950
    },
    {
      "char": "帽",
      "freq": 940
    },
    {
      "char": "冒",
      "freq": 930
    },
    {
      "char": "矛",
      "freq": 920
    },
    {
      "char": "茅",
      "freq": 910
    }
  ],
  "ㄇㄟ": [
    {
      "char": "沒",
      "freq": 970
    },
    {
      "char": "美",
      "freq": 960
    },
    {
      "char": "每",
      "freq": 950
    },
    {
      "char": "妹",
      "freq": 940
    },
    {
      "char": "梅",
      "freq": 930
    },
    {
      "char": "眉",
      "freq": 920
    },
    {
      "char": "媒",
      "freq": 910
    }
  ],
  "ㄇㄣ": [
    {
      "char": "門",
      "freq": 960
    },
    {
      "char": "們",
      "freq": 950
    },
    {
      "char": "悶",
      "freq": 940
    },
    {
      "char": "捫",
      "freq": 920
    }
  ],
  "ㄇㄥ": [
    {
      "char": "夢",
      "freq": 960
    },
    {
      "char": "猛",
      "freq": 950
    },
    {
      "char": "蒙",
      "freq": 940
    },
    {
      "char": "盟",
      "freq": 930
    },
    {
      "char": "萌",
      "freq": 920
    },
    {
      "char": "孟",
      "freq": 910
    }
  ],
  "ㄇㄧ": [
    {
      "char": "米",
      "freq": 960
    },
    {
      "char": "密",
      "freq": 950
    },
    {
      "char": "迷",
      "freq": 940
    },
    {
      "char": "秘",
      "freq": 930
    },
    {
      "char": "蜜",
      "freq": 920
    },
    {
      "char": "謎",
      "freq": 910
    }
  ],
  "ㄇㄧㄝ": [
    {
      "char": "滅",
      "freq": 950
    },
    {
      "char": "蔑",
      "freq": 920
    }
  ],
  "ㄇㄧㄠ": [
    {
      "char": "妙",
      "freq": 950
    },
    {
      "char": "秒",
      "freq": 940
    },
    {
      "char": "苗",
      "freq": 930
    },
    {
      "char": "描",
      "freq": 920
    },
    {
      "char": "廟",
      "freq": 910
    }
  ],
  "ㄇㄧㄢ": [
    {
      "char": "面",
      "freq": 960
    },
    {
      "char": "免",
      "freq": 950
    },
    {
      "char": "棉",
      "freq": 940
    },
    {
      "char": "眠",
      "freq": 930
    },
    {
      "char": "綿",
      "freq": 920
    },
    {
      "char": "勉",
      "freq": 910
    }
  ],
  "ㄇㄧㄣ": [
    {
      "char": "民",
      "freq": 960
    },
    {
      "char": "敏",
      "freq": 950
    },
    {
      "char": "閩",
      "freq": 930
    }
  ],
  "ㄇㄧㄥ": [
    {
      "char": "明",
      "freq": 970
    },
    {
      "char": "名",
      "freq": 960
    },
    {
      "char": "命",
      "freq": 950
    },
    {
      "char": "鳴",
      "freq": 930
    },
    {
      "char": "銘",
      "freq": 920
    }
  ],
  "ㄇㄛ": [
    {
      "char": "摸",
      "freq": 950
    },
    {
      "char": "模",
      "freq": 940
    },
    {
      "char": "磨",
      "freq": 930
    },
    {
      "char": "魔",
      "freq": 920
    },
    {
      "char": "莫",
      "freq": 910
    },
    {
      "char": "墨",
      "freq": 900
    },
    {
      "char": "默",
      "freq": 890
    }
  ],
  "ㄇㄡ": [
    {
      "char": "某",
      "freq": 950
    },
    {
      "char": "謀",
      "freq": 940
    },
    {
      "char": "牟",
      "freq": 920
    }
  ],
  "ㄇㄨ": [
    {
      "char": "母",
      "freq": 960
    },
    {
      "char": "木",
      "freq": 950
    },
    {
      "char": "目",
      "freq": 940
    },
    {
      "char": "牧",
      "freq": 930
    },
    {
      "char": "墓",
      "freq": 920
    },
    {
      "char": "幕",
      "freq": 910
    },
    {
      "char": "慕",
      "freq": 900
    }
  ],
  "ㄈㄚ": [
    {
      "char": "法",
      "freq": 970
    },
    {
      "char": "發",
      "freq": 960
    },
    {
      "char": "罰",
      "freq": 940
    },
    {
      "char": "乏",
      "freq": 930
    },
    {
      "char": "髮",
      "freq": 920
    },
    {
      "char": "伐",
      "freq": 910
    }
  ],
  "ㄈㄢ": [
    {
      "char": "反",
      "freq": 960
    },
    {
      "char": "飯",
      "freq": 950
    },
    {
      "char": "犯",
      "freq": 940
    },
    {
      "char": "範",
      "freq": 930
    },
    {
      "char": "凡",
      "freq": 920
    },
    {
      "char": "煩",
      "freq": 910
    },
    {
      "char": "繁",
      "freq": 900
    },
    {
      "char": "翻",
      "freq": 890
    }
  ],
  "ㄈㄤ": [
    {
      "char": "方",
      "freq": 970
    },
    {
      "char": "放",
      "freq": 960
    },
    {
      "char": "房",
      "freq": 950
    },
    {
      "char": "防",
      "freq": 940
    },
    {
      "char": "訪",
      "freq": 930
    },
    {
      "char": "仿",
      "freq": 920
    },
    {
      "char": "芳",
      "freq": 910
    }
  ],
  "ㄈㄟ": [
    {
      "char": "非",
      "freq": 960
    },
    {
      "char": "飛",
      "freq": 950
    },
    {
      "char": "費",
      "freq": 940
    },
    {
      "char": "肥",
      "freq": 930
    },
    {
      "char": "廢",
      "freq": 920
    },
    {
      "char": "肺",
      "freq": 910
    }
  ],
  "ㄈㄣ": [
    {
      "char": "分",
      "freq": 970
    },
    {
      "char": "份",
      "freq": 960
    },
    {
      "char": "粉",
      "freq": 940
    },
    {
      "char": "奮",
      "freq": 930
    },
    {
      "char": "紛",
      "freq": 920
    },
    {
      "char": "墳",
      "freq": 910
    }
  ],
  "ㄈㄥ": [
    {
      "char": "風",
      "freq": 970
    },
    {
      "char": "封",
      "freq": 950
    },
    {
      "char": "豐",
      "freq": 940
    },
    {
      "char": "蜂",
      "freq": 930
    },
    {
      "char": "瘋",
      "freq": 920
    },
    {
      "char": "縫",
      "freq": 910
    },
    {
      "char": "鋒",
      "freq": 900
    }
  ],
  "ㄈㄛ": [
    {
      "char": "佛",
      "freq": 960
    }
  ],
  "ㄈㄨ": [
    {
      "char": "夫",
      "freq": 960
    },
    {
      "char": "服",
      "freq": 950
    },
    {
      "char": "福",
      "freq": 940
    },
    {
      "char": "付",
      "freq": 930
    },
    {
      "char": "富",
      "freq": 920
    },
    {
      "char": "負",
      "freq": 910
    },
    {
      "char": "府",
      "freq": 900
    },
    {
      "char": "復",
      "freq": 890
    },
    {
      "char": "父",
      "freq": 880
    },
    {
      "char": "婦",
      "freq": 870
    },
    {
      "char": "腐",
      "freq": 860
    },
    {
      "char": "符",
      "freq": 850
    }
  ],
  "ㄉㄚ": [
    {
      "char": "大",
      "freq": 999
    },
    {
      "char": "打",
      "freq": 970
    },
    {
      "char": "答",
      "freq": 940
    },
    {
      "char": "達",
      "freq": 930
    },
    {
      "char": "搭",
      "freq": 920
    }
  ],
  "ㄉㄞ": [
    {
      "char": "代",
      "freq": 960
    },
    {
      "char": "帶",
      "freq": 950
    },
    {
      "char": "待",
      "freq": 940
    },
    {
      "char": "戴",
      "freq": 930
    },
    {
      "char": "袋",
      "freq": 920
    },
    {
      "char": "呆",
      "freq": 910
    }
  ],
  "ㄉㄢ": [
    {
      "char": "但",
      "freq": 960
    },
    {
      "char": "單",
      "freq": 950
    },
    {
      "char": "擔",
      "freq": 940
    },
    {
      "char": "蛋",
      "freq": 930
    },
    {
      "char": "淡",
      "freq": 920
    },
    {
      "char": "彈",
      "freq": 910
    },
    {
      "char": "膽",
      "freq": 900
    }
  ],
  "ㄉㄤ": [
    {
      "char": "當",
      "freq": 970
    },
    {
      "char": "黨",
      "freq": 950
    },
    {
      "char": "擋",
      "freq": 940
    },
    {
      "char": "檔",
      "freq": 930
    }
  ],
  "ㄉㄠ": [
    {
      "char": "到",
      "freq": 970
    },
    {
      "char": "道",
      "freq": 960
    },
    {
      "char": "刀",
      "freq": 950
    },
    {
      "char": "導",
      "freq": 940
    },
    {
      "char": "倒",
      "freq": 930
    },
    {
      "char": "島",
      "freq": 920
    },
    {
      "char": "稻",
      "freq": 910
    }
  ],
  "ㄉㄜ": [
    {
      "char": "的",
      "freq": 999
    },
    {
      "char": "得",
      "freq": 990
    },
    {
      "char": "德",
      "freq": 950
    }
  ],
  "ㄉㄥ": [
    {
      "char": "等",
      "freq": 960
    },
    {
      "char": "燈",
      "freq": 950
    },
    {
      "char": "登",
      "freq": 940
    },
    {
      "char": "鄧",
      "freq": 930
    }
  ],
  "ㄉㄧ": [
    {
      "char": "的",
      "freq": 999
    },
    {
      "char": "地",
      "freq": 990
    },
    {
      "char": "低",
      "freq": 960
    },
    {
      "char": "底",
      "freq": 950
    },
    {
      "char": "弟",
      "freq": 940
    },
    {
      "char": "第",
      "freq": 930
    },
    {
      "char": "敵",
      "freq": 920
    },
    {
      "char": "滴",
      "freq": 910
    }
  ],
  "ㄉㄧㄝ": [
    {
      "char": "跌",
      "freq": 950
    },
    {
      "char": "爹",
      "freq": 940
    },
    {
      "char": "蝶",
      "freq": 930
    },
    {
      "char": "碟",
      "freq": 920
    },
    {
      "char": "疊",
      "freq": 910
    }
  ],
  "ㄉㄧㄠ": [
    {
      "char": "調",
      "freq": 960
    },
    {
      "char": "掉",
      "freq": 950
    },
    {
      "char": "釣",
      "freq": 940
    },
    {
      "char": "雕",
      "freq": 930
    },
    {
      "char": "吊",
      "freq": 920
    }
  ],
  "ㄉㄧㄢ": [
    {
      "char": "點",
      "freq": 970
    },
    {
      "char": "電",
      "freq": 960
    },
    {
      "char": "店",
      "freq": 950
    },
    {
      "char": "典",
      "freq": 940
    },
    {
      "char": "殿",
      "freq": 930
    },
    {
      "char": "墊",
      "freq": 920
    }
  ],
  "ㄉㄧㄥ": [
    {
      "char": "定",
      "freq": 970
    },
    {
      "char": "頂",
      "freq": 950
    },
    {
      "char": "丁",
      "freq": 940
    },
    {
      "char": "釘",
      "freq": 930
    },
    {
      "char": "鼎",
      "freq": 920
    }
  ],
  "ㄉㄨ": [
    {
      "char": "都",
      "freq": 970
    },
    {
      "char": "讀",
      "freq": 960
    },
    {
      "char": "度",
      "freq": 950
    },
    {
      "char": "毒",
      "freq": 940
    },
    {
      "char": "獨",
      "freq": 930
    },
    {
      "char": "堵",
      "freq": 920
    },
    {
      "char": "杜",
      "freq": 910
    }
  ],
  "ㄉㄨㄟ": [
    {
      "char": "對",
      "freq": 970
    },
    {
      "char": "隊",
      "freq": 960
    }
  ],
  "ㄉㄨㄢ": [
    {
      "char": "短",
      "freq": 960
    },
    {
      "char": "段",
      "freq": 950
    },
    {
      "char": "斷",
      "freq": 940
    },
    {
      "char": "端",
      "freq": 930
    }
  ],
  "ㄉㄨㄥ": [
    {
      "char": "動",
      "freq": 970
    },
    {
      "char": "東",
      "freq": 960
    },
    {
      "char": "冬",
      "freq": 940
    },
    {
      "char": "懂",
      "freq": 930
    },
    {
      "char": "洞",
      "freq": 920
    },
    {
      "char": "凍",
      "freq": 910
    }
  ],
  "ㄊㄚ": [
    {
      "char": "他",
      "freq": 999
    },
    {
      "char": "她",
      "freq": 998
    },
    {
      "char": "它",
      "freq": 990
    },
    {
      "char": "塔",
      "freq": 940
    },
    {
      "char": "踏",
      "freq": 930
    },
    {
      "char": "塌",
      "freq": 920
    }
  ],
  "ㄊㄞ": [
    {
      "char": "太",
      "freq": 960
    },
    {
      "char": "台",
      "freq": 950
    },
    {
      "char": "態",
      "freq": 940
    },
    {
      "char": "泰",
      "freq": 930
    },
    {
      "char": "抬",
      "freq": 920
    },
    {
      "char": "胎",
      "freq": 910
    }
  ],
  "ㄊㄢ": [
    {
      "char": "談",
      "freq": 960
    },
    {
      "char": "彈",
      "freq": 950
    },
    {
      "char": "嘆",
      "freq": 940
    },
    {
      "char": "碳",
      "freq": 930
    },
    {
      "char": "灘",
      "freq": 920
    },
    {
      "char": "貪",
      "freq": 910
    },
    {
      "char": "攤",
      "freq": 900
    }
  ],
  "ㄊㄤ": [
    {
      "char": "堂",
      "freq": 960
    },
    {
      "char": "糖",
      "freq": 950
    },
    {
      "char": "湯",
      "freq": 940
    },
    {
      "char": "唐",
      "freq": 930
    },
    {
      "char": "燙",
      "freq": 920
    },
    {
      "char": "趟",
      "freq": 910
    }
  ],
  "ㄊㄠ": [
    {
      "char": "套",
      "freq": 960
    },
    {
      "char": "桃",
      "freq": 950
    },
    {
      "char": "逃",
      "freq": 940
    },
    {
      "char": "討",
      "freq": 930
    },
    {
      "char": "陶",
      "freq": 920
    },
    {
      "char": "淘",
      "freq": 910
    }
  ],
  "ㄊㄜ": [
    {
      "char": "特",
      "freq": 960
    }
  ],
  "ㄊㄥ": [
    {
      "char": "疼",
      "freq": 950
    },
    {
      "char": "騰",
      "freq": 940
    }
  ],
  "ㄊㄧ": [
    {
      "char": "提",
      "freq": 960
    },
    {
      "char": "題",
      "freq": 950
    },
    {
      "char": "體",
      "freq": 940
    },
    {
      "char": "替",
      "freq": 930
    },
    {
      "char": "踢",
      "freq": 920
    },
    {
      "char": "剃",
      "freq": 910
    }
  ],
  "ㄊㄧㄝ": [
    {
      "char": "貼",
      "freq": 950
    },
    {
      "char": "鐵",
      "freq": 940
    },
    {
      "char": "帖",
      "freq": 920
    }
  ],
  "ㄊㄧㄠ": [
    {
      "char": "條",
      "freq": 960
    },
    {
      "char": "跳",
      "freq": 950
    },
    {
      "char": "挑",
      "freq": 940
    },
    {
      "char": "調",
      "freq": 930
    }
  ],
  "ㄊㄧㄢ": [
    {
      "char": "天",
      "freq": 999
    },
    {
      "char": "田",
      "freq": 960
    },
    {
      "char": "填",
      "freq": 940
    },
    {
      "char": "甜",
      "freq": 930
    },
    {
      "char": "添",
      "freq": 920
    }
  ],
  "ㄊㄧㄥ": [
    {
      "char": "聽",
      "freq": 960
    },
    {
      "char": "停",
      "freq": 950
    },
    {
      "char": "廳",
      "freq": 940
    },
    {
      "char": "庭",
      "freq": 930
    },
    {
      "char": "挺",
      "freq": 920
    },
    {
      "char": "亭",
      "freq": 910
    }
  ],
  "ㄊㄨ": [
    {
      "char": "土",
      "freq": 960
    },
    {
      "char": "突",
      "freq": 950
    },
    {
      "char": "圖",
      "freq": 940
    },
    {
      "char": "吐",
      "freq": 930
    },
    {
      "char": "兔",
      "freq": 920
    },
    {
      "char": "途",
      "freq": 910
    },
    {
      "char": "徒",
      "freq": 900
    }
  ],
  "ㄊㄨㄟ": [
    {
      "char": "退",
      "freq": 960
    },
    {
      "char": "推",
      "freq": 950
    },
    {
      "char": "腿",
      "freq": 940
    }
  ],
  "ㄊㄨㄢ": [
    {
      "char": "團",
      "freq": 960
    },
    {
      "char": "湍",
      "freq": 920
    }
  ],
  "ㄊㄨㄥ": [
    {
      "char": "同",
      "freq": 970
    },
    {
      "char": "通",
      "freq": 960
    },
    {
      "char": "痛",
      "freq": 950
    },
    {
      "char": "統",
      "freq": 940
    },
    {
      "char": "銅",
      "freq": 930
    },
    {
      "char": "童",
      "freq": 920
    },
    {
      "char": "桶",
      "freq": 910
    }
  ],
  "ㄋㄚ": [
    {
      "char": "那",
      "freq": 980
    },
    {
      "char": "拿",
      "freq": 960
    },
    {
      "char": "哪",
      "freq": 950
    },
    {
      "char": "納",
      "freq": 940
    }
  ],
  "ㄋㄞ": [
    {
      "char": "奶",
      "freq": 950
    },
    {
      "char": "乃",
      "freq": 940
    },
    {
      "char": "耐",
      "freq": 930
    },
    {
      "char": "奈",
      "freq": 920
    }
  ],
  "ㄋㄢ": [
    {
      "char": "南",
      "freq": 960
    },
    {
      "char": "男",
      "freq": 950
    },
    {
      "char": "難",
      "freq": 940
    },
    {
      "char": "暖",
      "freq": 910
    }
  ],
  "ㄋㄤ": [
    {
      "char": "囊",
      "freq": 930
    }
  ],
  "ㄋㄠ": [
    {
      "char": "腦",
      "freq": 960
    },
    {
      "char": "鬧",
      "freq": 950
    },
    {
      "char": "惱",
      "freq": 940
    }
  ],
  "ㄋㄟ": [
    {
      "char": "內",
      "freq": 960
    }
  ],
  "ㄋㄥ": [
    {
      "char": "能",
      "freq": 970
    },
    {
      "char": "嫩",
      "freq": 920
    }
  ],
  "ㄋㄧ": [
    {
      "char": "你",
      "freq": 999
    },
    {
      "char": "泥",
      "freq": 930
    },
    {
      "char": "逆",
      "freq": 920
    },
    {
      "char": "匿",
      "freq": 910
    }
  ],
  "ㄋㄧㄝ": [
    {
      "char": "捏",
      "freq": 930
    },
    {
      "char": "聶",
      "freq": 920
    }
  ],
  "ㄋㄧㄠ": [
    {
      "char": "鳥",
      "freq": 950
    },
    {
      "char": "尿",
      "freq": 930
    }
  ],
  "ㄋㄧㄢ": [
    {
      "char": "年",
      "freq": 970
    },
    {
      "char": "念",
      "freq": 960
    },
    {
      "char": "唸",
      "freq": 940
    },
    {
      "char": "粘",
      "freq": 930
    }
  ],
  "ㄋㄧㄣ": [
    {
      "char": "您",
      "freq": 960
    }
  ],
  "ㄋㄧㄤ": [
    {
      "char": "娘",
      "freq": 950
    },
    {
      "char": "釀",
      "freq": 930
    }
  ],
  "ㄋㄧㄥ": [
    {
      "char": "寧",
      "freq": 950
    },
    {
      "char": "凝",
      "freq": 940
    },
    {
      "char": "擰",
      "freq": 920
    }
  ],
  "ㄋㄨ": [
    {
      "char": "努",
      "freq": 950
    },
    {
      "char": "怒",
      "freq": 940
    }
  ],
  "ㄋㄩ": [
    {
      "char": "女",
      "freq": 970
    },
    {
      "char": "呂",
      "freq": 930
    }
  ],
  "ㄋㄨㄥ": [
    {
      "char": "農",
      "freq": 950
    },
    {
      "char": "濃",
      "freq": 940
    },
    {
      "char": "弄",
      "freq": 930
    }
  ],
  "ㄌㄚ": [
    {
      "char": "拉",
      "freq": 960
    },
    {
      "char": "啦",
      "freq": 950
    },
    {
      "char": "辣",
      "freq": 930
    },
    {
      "char": "垃",
      "freq": 920
    }
  ],
  "ㄌㄞ": [
    {
      "char": "來",
      "freq": 980
    },
    {
      "char": "賴",
      "freq": 920
    },
    {
      "char": "萊",
      "freq": 910
    }
  ],
  "ㄌㄢ": [
    {
      "char": "藍",
      "freq": 960
    },
    {
      "char": "蘭",
      "freq": 950
    },
    {
      "char": "懶",
      "freq": 940
    },
    {
      "char": "爛",
      "freq": 930
    },
    {
      "char": "攔",
      "freq": 920
    }
  ],
  "ㄌㄤ": [
    {
      "char": "浪",
      "freq": 950
    },
    {
      "char": "狼",
      "freq": 940
    },
    {
      "char": "郎",
      "freq": 930
    },
    {
      "char": "朗",
      "freq": 920
    }
  ],
  "ㄌㄠ": [
    {
      "char": "老",
      "freq": 970
    },
    {
      "char": "勞",
      "freq": 950
    },
    {
      "char": "牢",
      "freq": 940
    },
    {
      "char": "撈",
      "freq": 920
    }
  ],
  "ㄌㄜ": [
    {
      "char": "了",
      "freq": 990
    },
    {
      "char": "樂",
      "freq": 970
    },
    {
      "char": "勒",
      "freq": 930
    }
  ],
  "ㄌㄟ": [
    {
      "char": "累",
      "freq": 950
    },
    {
      "char": "雷",
      "freq": 940
    },
    {
      "char": "類",
      "freq": 930
    },
    {
      "char": "淚",
      "freq": 920
    },
    {
      "char": "壘",
      "freq": 910
    }
  ],
  "ㄌㄥ": [
    {
      "char": "冷",
      "freq": 960
    },
    {
      "char": "愣",
      "freq": 930
    }
  ],
  "ㄌㄧ": [
    {
      "char": "力",
      "freq": 970
    },
    {
      "char": "里",
      "freq": 960
    },
    {
      "char": "理",
      "freq": 950
    },
    {
      "char": "利",
      "freq": 940
    },
    {
      "char": "立",
      "freq": 930
    },
    {
      "char": "禮",
      "freq": 920
    },
    {
      "char": "李",
      "freq": 910
    },
    {
      "char": "離",
      "freq": 900
    }
  ],
  "ㄌㄧㄝ": [
    {
      "char": "列",
      "freq": 950
    },
    {
      "char": "烈",
      "freq": 940
    },
    {
      "char": "裂",
      "freq": 930
    },
    {
      "char": "劣",
      "freq": 920
    }
  ],
  "ㄌㄧㄠ": [
    {
      "char": "了",
      "freq": 990
    },
    {
      "char": "料",
      "freq": 950
    },
    {
      "char": "聊",
      "freq": 940
    },
    {
      "char": "療",
      "freq": 930
    },
    {
      "char": "遼",
      "freq": 920
    }
  ],
  "ㄌㄧㄢ": [
    {
      "char": "連",
      "freq": 960
    },
    {
      "char": "練",
      "freq": 950
    },
    {
      "char": "臉",
      "freq": 940
    },
    {
      "char": "聯",
      "freq": 930
    },
    {
      "char": "戀",
      "freq": 920
    },
    {
      "char": "蓮",
      "freq": 910
    }
  ],
  "ㄌㄧㄣ": [
    {
      "char": "林",
      "freq": 960
    },
    {
      "char": "鄰",
      "freq": 950
    },
    {
      "char": "臨",
      "freq": 940
    },
    {
      "char": "淋",
      "freq": 930
    }
  ],
  "ㄌㄧㄤ": [
    {
      "char": "兩",
      "freq": 970
    },
    {
      "char": "量",
      "freq": 960
    },
    {
      "char": "涼",
      "freq": 950
    },
    {
      "char": "良",
      "freq": 940
    },
    {
      "char": "亮",
      "freq": 930
    },
    {
      "char": "糧",
      "freq": 920
    }
  ],
  "ㄌㄧㄥ": [
    {
      "char": "領",
      "freq": 960
    },
    {
      "char": "靈",
      "freq": 950
    },
    {
      "char": "零",
      "freq": 940
    },
    {
      "char": "令",
      "freq": 930
    },
    {
      "char": "另",
      "freq": 920
    },
    {
      "char": "鈴",
      "freq": 910
    }
  ],
  "ㄌㄨ": [
    {
      "char": "路",
      "freq": 960
    },
    {
      "char": "錄",
      "freq": 950
    },
    {
      "char": "陸",
      "freq": 940
    },
    {
      "char": "露",
      "freq": 930
    },
    {
      "char": "盧",
      "freq": 920
    },
    {
      "char": "魯",
      "freq": 910
    },
    {
      "char": "鹿",
      "freq": 900
    }
  ],
  "ㄌㄩ": [
    {
      "char": "律",
      "freq": 960
    },
    {
      "char": "綠",
      "freq": 950
    },
    {
      "char": "旅",
      "freq": 940
    },
    {
      "char": "慮",
      "freq": 930
    },
    {
      "char": "濾",
      "freq": 920
    }
  ],
  "ㄌㄨㄢ": [
    {
      "char": "亂",
      "freq": 960
    },
    {
      "char": "卵",
      "freq": 940
    }
  ],
  "ㄌㄨㄥ": [
    {
      "char": "龍",
      "freq": 960
    },
    {
      "char": "隆",
      "freq": 950
    },
    {
      "char": "弄",
      "freq": 930
    },
    {
      "char": "聾",
      "freq": 920
    }
  ],
  "ㄍㄚ": [
    {
      "char": "嘎",
      "freq": 930
    }
  ],
  "ㄍㄞ": [
    {
      "char": "該",
      "freq": 960
    },
    {
      "char": "改",
      "freq": 950
    },
    {
      "char": "蓋",
      "freq": 940
    },
    {
      "char": "概",
      "freq": 930
    }
  ],
  "ㄍㄢ": [
    {
      "char": "幹",
      "freq": 960
    },
    {
      "char": "感",
      "freq": 950
    },
    {
      "char": "敢",
      "freq": 940
    },
    {
      "char": "趕",
      "freq": 930
    },
    {
      "char": "甘",
      "freq": 920
    },
    {
      "char": "肝",
      "freq": 910
    }
  ],
  "ㄍㄤ": [
    {
      "char": "剛",
      "freq": 960
    },
    {
      "char": "鋼",
      "freq": 950
    },
    {
      "char": "港",
      "freq": 940
    },
    {
      "char": "崗",
      "freq": 930
    },
    {
      "char": "綱",
      "freq": 920
    }
  ],
  "ㄍㄠ": [
    {
      "char": "高",
      "freq": 970
    },
    {
      "char": "告",
      "freq": 960
    },
    {
      "char": "搞",
      "freq": 950
    },
    {
      "char": "稿",
      "freq": 940
    },
    {
      "char": "糕",
      "freq": 930
    }
  ],
  "ㄍㄜ": [
    {
      "char": "個",
      "freq": 990
    },
    {
      "char": "各",
      "freq": 960
    },
    {
      "char": "歌",
      "freq": 950
    },
    {
      "char": "格",
      "freq": 940
    },
    {
      "char": "隔",
      "freq": 930
    },
    {
      "char": "割",
      "freq": 920
    },
    {
      "char": "革",
      "freq": 910
    },
    {
      "char": "閣",
      "freq": 900
    }
  ],
  "ㄍㄟ": [
    {
      "char": "給",
      "freq": 970
    }
  ],
  "ㄍㄣ": [
    {
      "char": "根",
      "freq": 960
    },
    {
      "char": "跟",
      "freq": 950
    },
    {
      "char": "亙",
      "freq": 920
    }
  ],
  "ㄍㄥ": [
    {
      "char": "更",
      "freq": 970
    },
    {
      "char": "耕",
      "freq": 940
    },
    {
      "char": "庚",
      "freq": 920
    }
  ],
  "ㄍㄨ": [
    {
      "char": "古",
      "freq": 960
    },
    {
      "char": "故",
      "freq": 950
    },
    {
      "char": "骨",
      "freq": 940
    },
    {
      "char": "鼓",
      "freq": 930
    },
    {
      "char": "固",
      "freq": 920
    },
    {
      "char": "顧",
      "freq": 910
    },
    {
      "char": "孤",
      "freq": 900
    },
    {
      "char": "估",
      "freq": 890
    }
  ],
  "ㄍㄨㄚ": [
    {
      "char": "瓜",
      "freq": 950
    },
    {
      "char": "刮",
      "freq": 940
    },
    {
      "char": "掛",
      "freq": 930
    },
    {
      "char": "寡",
      "freq": 920
    }
  ],
  "ㄍㄨㄞ": [
    {
      "char": "怪",
      "freq": 950
    },
    {
      "char": "乖",
      "freq": 940
    },
    {
      "char": "拐",
      "freq": 930
    }
  ],
  "ㄍㄨㄢ": [
    {
      "char": "關",
      "freq": 970
    },
    {
      "char": "管",
      "freq": 960
    },
    {
      "char": "官",
      "freq": 950
    },
    {
      "char": "觀",
      "freq": 940
    },
    {
      "char": "館",
      "freq": 930
    },
    {
      "char": "慣",
      "freq": 920
    },
    {
      "char": "冠",
      "freq": 910
    }
  ],
  "ㄍㄨㄤ": [
    {
      "char": "光",
      "freq": 970
    },
    {
      "char": "廣",
      "freq": 960
    },
    {
      "char": "逛",
      "freq": 940
    }
  ],
  "ㄍㄨㄟ": [
    {
      "char": "貴",
      "freq": 960
    },
    {
      "char": "鬼",
      "freq": 950
    },
    {
      "char": "規",
      "freq": 940
    },
    {
      "char": "歸",
      "freq": 930
    },
    {
      "char": "龜",
      "freq": 920
    }
  ],
  "ㄍㄨㄣ": [
    {
      "char": "棍",
      "freq": 930
    },
    {
      "char": "滾",
      "freq": 920
    }
  ],
  "ㄍㄨㄥ": [
    {
      "char": "工",
      "freq": 970
    },
    {
      "char": "公",
      "freq": 960
    },
    {
      "char": "共",
      "freq": 950
    },
    {
      "char": "功",
      "freq": 940
    },
    {
      "char": "供",
      "freq": 930
    },
    {
      "char": "宮",
      "freq": 920
    },
    {
      "char": "攻",
      "freq": 910
    },
    {
      "char": "恭",
      "freq": 900
    }
  ],
  "ㄍㄨㄛ": [
    {
      "char": "國",
      "freq": 980
    },
    {
      "char": "過",
      "freq": 970
    },
    {
      "char": "果",
      "freq": 960
    },
    {
      "char": "鍋",
      "freq": 940
    },
    {
      "char": "裹",
      "freq": 920
    }
  ],
  "ㄎㄚ": [
    {
      "char": "卡",
      "freq": 960
    },
    {
      "char": "咖",
      "freq": 940
    }
  ],
  "ㄎㄞ": [
    {
      "char": "開",
      "freq": 970
    },
    {
      "char": "凱",
      "freq": 940
    }
  ],
  "ㄎㄢ": [
    {
      "char": "看",
      "freq": 980
    },
    {
      "char": "砍",
      "freq": 930
    },
    {
      "char": "刊",
      "freq": 920
    }
  ],
  "ㄎㄤ": [
    {
      "char": "康",
      "freq": 960
    },
    {
      "char": "抗",
      "freq": 950
    },
    {
      "char": "扛",
      "freq": 930
    }
  ],
  "ㄎㄠ": [
    {
      "char": "考",
      "freq": 960
    },
    {
      "char": "靠",
      "freq": 950
    },
    {
      "char": "烤",
      "freq": 940
    }
  ],
  "ㄎㄜ": [
    {
      "char": "可",
      "freq": 970
    },
    {
      "char": "課",
      "freq": 960
    },
    {
      "char": "科",
      "freq": 950
    },
    {
      "char": "克",
      "freq": 940
    },
    {
      "char": "客",
      "freq": 930
    },
    {
      "char": "棵",
      "freq": 920
    },
    {
      "char": "刻",
      "freq": 910
    },
    {
      "char": "渴",
      "freq": 900
    }
  ],
  "ㄎㄣ": [
    {
      "char": "肯",
      "freq": 960
    },
    {
      "char": "啃",
      "freq": 930
    },
    {
      "char": "懇",
      "freq": 920
    }
  ],
  "ㄎㄥ": [
    {
      "char": "坑",
      "freq": 940
    },
    {
      "char": "鏗",
      "freq": 920
    }
  ],
  "ㄎㄨ": [
    {
      "char": "苦",
      "freq": 960
    },
    {
      "char": "哭",
      "freq": 950
    },
    {
      "char": "庫",
      "freq": 940
    },
    {
      "char": "酷",
      "freq": 930
    },
    {
      "char": "枯",
      "freq": 920
    }
  ],
  "ㄎㄨㄚ": [
    {
      "char": "誇",
      "freq": 950
    },
    {
      "char": "跨",
      "freq": 940
    },
    {
      "char": "垮",
      "freq": 930
    }
  ],
  "ㄎㄨㄞ": [
    {
      "char": "快",
      "freq": 970
    },
    {
      "char": "塊",
      "freq": 950
    },
    {
      "char": "筷",
      "freq": 930
    }
  ],
  "ㄎㄨㄢ": [
    {
      "char": "寬",
      "freq": 950
    },
    {
      "char": "款",
      "freq": 940
    }
  ],
  "ㄎㄨㄤ": [
    {
      "char": "狂",
      "freq": 950
    },
    {
      "char": "框",
      "freq": 940
    },
    {
      "char": "礦",
      "freq": 930
    },
    {
      "char": "況",
      "freq": 920
    }
  ],
  "ㄎㄨㄣ": [
    {
      "char": "困",
      "freq": 960
    },
    {
      "char": "昆",
      "freq": 940
    },
    {
      "char": "捆",
      "freq": 930
    }
  ],
  "ㄎㄨㄥ": [
    {
      "char": "空",
      "freq": 970
    },
    {
      "char": "孔",
      "freq": 950
    },
    {
      "char": "控",
      "freq": 940
    },
    {
      "char": "恐",
      "freq": 930
    }
  ],
  "ㄎㄡ": [
    {
      "char": "口",
      "freq": 970
    },
    {
      "char": "扣",
      "freq": 950
    },
    {
      "char": "摳",
      "freq": 930
    }
  ],
  "ㄏㄚ": [
    {
      "char": "哈",
      "freq": 960
    }
  ],
  "ㄏㄞ": [
    {
      "char": "海",
      "freq": 960
    },
    {
      "char": "還",
      "freq": 950
    },
    {
      "char": "害",
      "freq": 940
    },
    {
      "char": "孩",
      "freq": 930
    }
  ],
  "ㄏㄢ": [
    {
      "char": "漢",
      "freq": 960
    },
    {
      "char": "含",
      "freq": 950
    },
    {
      "char": "喊",
      "freq": 940
    },
    {
      "char": "寒",
      "freq": 930
    },
    {
      "char": "汗",
      "freq": 920
    },
    {
      "char": "韓",
      "freq": 910
    }
  ],
  "ㄏㄤ": [
    {
      "char": "行",
      "freq": 960
    },
    {
      "char": "航",
      "freq": 950
    },
    {
      "char": "杭",
      "freq": 930
    }
  ],
  "ㄏㄠ": [
    {
      "char": "好",
      "freq": 990
    },
    {
      "char": "號",
      "freq": 960
    },
    {
      "char": "豪",
      "freq": 940
    },
    {
      "char": "毫",
      "freq": 930
    },
    {
      "char": "耗",
      "freq": 920
    }
  ],
  "ㄏㄜ": [
    {
      "char": "和",
      "freq": 980
    },
    {
      "char": "河",
      "freq": 960
    },
    {
      "char": "何",
      "freq": 950
    },
    {
      "char": "合",
      "freq": 940
    },
    {
      "char": "賀",
      "freq": 930
    },
    {
      "char": "喝",
      "freq": 920
    },
    {
      "char": "核",
      "freq": 910
    }
  ],
  "ㄏㄟ": [
    {
      "char": "黑",
      "freq": 960
    },
    {
      "char": "嘿",
      "freq": 930
    }
  ],
  "ㄏㄣ": [
    {
      "char": "很",
      "freq": 980
    },
    {
      "char": "恨",
      "freq": 940
    },
    {
      "char": "狠",
      "freq": 930
    }
  ],
  "ㄏㄥ": [
    {
      "char": "恆",
      "freq": 950
    },
    {
      "char": "橫",
      "freq": 940
    },
    {
      "char": "哼",
      "freq": 920
    }
  ],
  "ㄏㄨ": [
    {
      "char": "湖",
      "freq": 960
    },
    {
      "char": "虎",
      "freq": 950
    },
    {
      "char": "戶",
      "freq": 940
    },
    {
      "char": "胡",
      "freq": 930
    },
    {
      "char": "護",
      "freq": 920
    },
    {
      "char": "互",
      "freq": 910
    },
    {
      "char": "乎",
      "freq": 900
    },
    {
      "char": "忽",
      "freq": 890
    },
    {
      "char": "壺",
      "freq": 880
    }
  ],
  "ㄏㄨㄚ": [
    {
      "char": "花",
      "freq": 970
    },
    {
      "char": "話",
      "freq": 960
    },
    {
      "char": "化",
      "freq": 950
    },
    {
      "char": "華",
      "freq": 940
    },
    {
      "char": "畫",
      "freq": 930
    },
    {
      "char": "划",
      "freq": 920
    }
  ],
  "ㄏㄨㄞ": [
    {
      "char": "壞",
      "freq": 960
    },
    {
      "char": "懷",
      "freq": 950
    },
    {
      "char": "淮",
      "freq": 930
    }
  ],
  "ㄏㄨㄢ": [
    {
      "char": "還",
      "freq": 970
    },
    {
      "char": "換",
      "freq": 960
    },
    {
      "char": "歡",
      "freq": 950
    },
    {
      "char": "環",
      "freq": 940
    },
    {
      "char": "患",
      "freq": 930
    },
    {
      "char": "幻",
      "freq": 920
    },
    {
      "char": "緩",
      "freq": 910
    }
  ],
  "ㄏㄨㄤ": [
    {
      "char": "黃",
      "freq": 960
    },
    {
      "char": "皇",
      "freq": 950
    },
    {
      "char": "荒",
      "freq": 940
    },
    {
      "char": "慌",
      "freq": 930
    },
    {
      "char": "晃",
      "freq": 920
    }
  ],
  "ㄏㄨㄟ": [
    {
      "char": "會",
      "freq": 980
    },
    {
      "char": "回",
      "freq": 970
    },
    {
      "char": "灰",
      "freq": 950
    },
    {
      "char": "慧",
      "freq": 940
    },
    {
      "char": "匯",
      "freq": 930
    },
    {
      "char": "毀",
      "freq": 920
    },
    {
      "char": "悔",
      "freq": 910
    }
  ],
  "ㄏㄨㄣ": [
    {
      "char": "婚",
      "freq": 950
    },
    {
      "char": "混",
      "freq": 940
    },
    {
      "char": "魂",
      "freq": 930
    },
    {
      "char": "昏",
      "freq": 920
    }
  ],
  "ㄏㄨㄥ": [
    {
      "char": "紅",
      "freq": 960
    },
    {
      "char": "洪",
      "freq": 950
    },
    {
      "char": "宏",
      "freq": 940
    },
    {
      "char": "虹",
      "freq": 930
    },
    {
      "char": "鴻",
      "freq": 920
    }
  ],
  "ㄏㄨㄛ": [
    {
      "char": "活",
      "freq": 970
    },
    {
      "char": "火",
      "freq": 960
    },
    {
      "char": "或",
      "freq": 950
    },
    {
      "char": "貨",
      "freq": 940
    },
    {
      "char": "獲",
      "freq": 930
    },
    {
      "char": "伙",
      "freq": 920
    }
  ],
  "ㄐㄧ": [
    {
      "char": "幾",
      "freq": 980
    },
    {
      "char": "及",
      "freq": 970
    },
    {
      "char": "己",
      "freq": 960
    },
    {
      "char": "機",
      "freq": 950
    },
    {
      "char": "雞",
      "freq": 940
    },
    {
      "char": "積",
      "freq": 930
    },
    {
      "char": "基",
      "freq": 920
    },
    {
      "char": "急",
      "freq": 910
    },
    {
      "char": "集",
      "freq": 900
    },
    {
      "char": "極",
      "freq": 890
    },
    {
      "char": "即",
      "freq": 880
    },
    {
      "char": "吉",
      "freq": 870
    }
  ],
  "ㄐㄧㄚ": [
    {
      "char": "家",
      "freq": 990
    },
    {
      "char": "加",
      "freq": 970
    },
    {
      "char": "假",
      "freq": 960
    },
    {
      "char": "價",
      "freq": 950
    },
    {
      "char": "架",
      "freq": 940
    },
    {
      "char": "嫁",
      "freq": 930
    },
    {
      "char": "夾",
      "freq": 920
    }
  ],
  "ㄐㄧㄝ": [
    {
      "char": "結",
      "freq": 960
    },
    {
      "char": "接",
      "freq": 950
    },
    {
      "char": "節",
      "freq": 940
    },
    {
      "char": "街",
      "freq": 930
    },
    {
      "char": "姐",
      "freq": 920
    },
    {
      "char": "解",
      "freq": 910
    },
    {
      "char": "借",
      "freq": 900
    },
    {
      "char": "界",
      "freq": 890
    },
    {
      "char": "階",
      "freq": 880
    }
  ],
  "ㄐㄧㄠ": [
    {
      "char": "教",
      "freq": 970
    },
    {
      "char": "叫",
      "freq": 960
    },
    {
      "char": "交",
      "freq": 950
    },
    {
      "char": "較",
      "freq": 940
    },
    {
      "char": "角",
      "freq": 930
    },
    {
      "char": "腳",
      "freq": 920
    },
    {
      "char": "焦",
      "freq": 910
    }
  ],
  "ㄐㄧㄢ": [
    {
      "char": "見",
      "freq": 970
    },
    {
      "char": "間",
      "freq": 960
    },
    {
      "char": "件",
      "freq": 950
    },
    {
      "char": "建",
      "freq": 940
    },
    {
      "char": "簡",
      "freq": 930
    },
    {
      "char": "剪",
      "freq": 920
    },
    {
      "char": "堅",
      "freq": 910
    },
    {
      "char": "肩",
      "freq": 900
    },
    {
      "char": "漸",
      "freq": 890
    }
  ],
  "ㄐㄧㄣ": [
    {
      "char": "金",
      "freq": 970
    },
    {
      "char": "今",
      "freq": 960
    },
    {
      "char": "近",
      "freq": 950
    },
    {
      "char": "進",
      "freq": 940
    },
    {
      "char": "禁",
      "freq": 930
    },
    {
      "char": "盡",
      "freq": 920
    },
    {
      "char": "緊",
      "freq": 910
    },
    {
      "char": "斤",
      "freq": 900
    }
  ],
  "ㄐㄧㄤ": [
    {
      "char": "將",
      "freq": 970
    },
    {
      "char": "講",
      "freq": 960
    },
    {
      "char": "江",
      "freq": 950
    },
    {
      "char": "降",
      "freq": 940
    },
    {
      "char": "獎",
      "freq": 930
    },
    {
      "char": "姜",
      "freq": 920
    },
    {
      "char": "漿",
      "freq": 910
    }
  ],
  "ㄐㄧㄥ": [
    {
      "char": "經",
      "freq": 970
    },
    {
      "char": "精",
      "freq": 960
    },
    {
      "char": "京",
      "freq": 950
    },
    {
      "char": "景",
      "freq": 940
    },
    {
      "char": "靜",
      "freq": 930
    },
    {
      "char": "境",
      "freq": 920
    },
    {
      "char": "鏡",
      "freq": 910
    },
    {
      "char": "警",
      "freq": 900
    },
    {
      "char": "敬",
      "freq": 890
    }
  ],
  "ㄐㄩ": [
    {
      "char": "居",
      "freq": 960
    },
    {
      "char": "局",
      "freq": 950
    },
    {
      "char": "舉",
      "freq": 940
    },
    {
      "char": "句",
      "freq": 930
    },
    {
      "char": "具",
      "freq": 920
    },
    {
      "char": "據",
      "freq": 910
    },
    {
      "char": "距",
      "freq": 900
    },
    {
      "char": "巨",
      "freq": 890
    }
  ],
  "ㄐㄩㄝ": [
    {
      "char": "覺",
      "freq": 960
    },
    {
      "char": "決",
      "freq": 950
    },
    {
      "char": "絕",
      "freq": 940
    },
    {
      "char": "角",
      "freq": 930
    },
    {
      "char": "爵",
      "freq": 920
    }
  ],
  "ㄐㄩㄢ": [
    {
      "char": "卷",
      "freq": 950
    },
    {
      "char": "捲",
      "freq": 940
    },
    {
      "char": "圈",
      "freq": 930
    },
    {
      "char": "倦",
      "freq": 920
    },
    {
      "char": "絹",
      "freq": 910
    }
  ],
  "ㄐㄩㄣ": [
    {
      "char": "軍",
      "freq": 960
    },
    {
      "char": "君",
      "freq": 950
    },
    {
      "char": "均",
      "freq": 940
    },
    {
      "char": "俊",
      "freq": 930
    }
  ],
  "ㄑㄧ": [
    {
      "char": "七",
      "freq": 960
    },
    {
      "char": "其",
      "freq": 950
    },
    {
      "char": "起",
      "freq": 940
    },
    {
      "char": "氣",
      "freq": 930
    },
    {
      "char": "奇",
      "freq": 920
    },
    {
      "char": "期",
      "freq": 910
    },
    {
      "char": "妻",
      "freq": 900
    },
    {
      "char": "棋",
      "freq": 890
    },
    {
      "char": "漆",
      "freq": 880
    }
  ],
  "ㄑㄧㄚ": [
    {
      "char": "恰",
      "freq": 940
    },
    {
      "char": "掐",
      "freq": 920
    }
  ],
  "ㄑㄧㄝ": [
    {
      "char": "切",
      "freq": 960
    },
    {
      "char": "且",
      "freq": 950
    },
    {
      "char": "茄",
      "freq": 920
    }
  ],
  "ㄑㄧㄠ": [
    {
      "char": "巧",
      "freq": 960
    },
    {
      "char": "橋",
      "freq": 950
    },
    {
      "char": "敲",
      "freq": 940
    },
    {
      "char": "悄",
      "freq": 930
    },
    {
      "char": "瞧",
      "freq": 920
    }
  ],
  "ㄑㄧㄢ": [
    {
      "char": "前",
      "freq": 970
    },
    {
      "char": "千",
      "freq": 960
    },
    {
      "char": "錢",
      "freq": 950
    },
    {
      "char": "淺",
      "freq": 940
    },
    {
      "char": "牽",
      "freq": 930
    },
    {
      "char": "簽",
      "freq": 920
    },
    {
      "char": "鉛",
      "freq": 910
    }
  ],
  "ㄑㄧㄣ": [
    {
      "char": "親",
      "freq": 960
    },
    {
      "char": "勤",
      "freq": 950
    },
    {
      "char": "琴",
      "freq": 940
    },
    {
      "char": "秦",
      "freq": 930
    },
    {
      "char": "侵",
      "freq": 920
    }
  ],
  "ㄑㄧㄤ": [
    {
      "char": "強",
      "freq": 960
    },
    {
      "char": "牆",
      "freq": 950
    },
    {
      "char": "搶",
      "freq": 940
    },
    {
      "char": "槍",
      "freq": 930
    }
  ],
  "ㄑㄧㄥ": [
    {
      "char": "清",
      "freq": 960
    },
    {
      "char": "請",
      "freq": 950
    },
    {
      "char": "情",
      "freq": 940
    },
    {
      "char": "輕",
      "freq": 930
    },
    {
      "char": "青",
      "freq": 920
    },
    {
      "char": "晴",
      "freq": 910
    },
    {
      "char": "慶",
      "freq": 900
    }
  ],
  "ㄑㄩ": [
    {
      "char": "去",
      "freq": 970
    },
    {
      "char": "區",
      "freq": 960
    },
    {
      "char": "曲",
      "freq": 950
    },
    {
      "char": "趣",
      "freq": 940
    },
    {
      "char": "取",
      "freq": 930
    },
    {
      "char": "娶",
      "freq": 920
    }
  ],
  "ㄑㄩㄝ": [
    {
      "char": "確",
      "freq": 960
    },
    {
      "char": "缺",
      "freq": 950
    },
    {
      "char": "卻",
      "freq": 940
    },
    {
      "char": "雀",
      "freq": 930
    }
  ],
  "ㄑㄩㄢ": [
    {
      "char": "全",
      "freq": 970
    },
    {
      "char": "權",
      "freq": 960
    },
    {
      "char": "圈",
      "freq": 950
    },
    {
      "char": "泉",
      "freq": 940
    },
    {
      "char": "拳",
      "freq": 930
    },
    {
      "char": "犬",
      "freq": 920
    }
  ],
  "ㄑㄩㄣ": [
    {
      "char": "群",
      "freq": 960
    },
    {
      "char": "裙",
      "freq": 940
    }
  ],
  "ㄒㄧ": [
    {
      "char": "西",
      "freq": 960
    },
    {
      "char": "希",
      "freq": 950
    },
    {
      "char": "洗",
      "freq": 940
    },
    {
      "char": "系",
      "freq": 930
    },
    {
      "char": "細",
      "freq": 920
    },
    {
      "char": "習",
      "freq": 910
    },
    {
      "char": "席",
      "freq": 900
    },
    {
      "char": "息",
      "freq": 890
    },
    {
      "char": "戲",
      "freq": 880
    }
  ],
  "ㄒㄧㄚ": [
    {
      "char": "下",
      "freq": 980
    },
    {
      "char": "夏",
      "freq": 960
    },
    {
      "char": "嚇",
      "freq": 940
    },
    {
      "char": "蝦",
      "freq": 930
    },
    {
      "char": "瞎",
      "freq": 920
    }
  ],
  "ㄒㄧㄝ": [
    {
      "char": "些",
      "freq": 960
    },
    {
      "char": "寫",
      "freq": 950
    },
    {
      "char": "謝",
      "freq": 940
    },
    {
      "char": "鞋",
      "freq": 930
    },
    {
      "char": "血",
      "freq": 920
    },
    {
      "char": "卸",
      "freq": 910
    },
    {
      "char": "協",
      "freq": 900
    }
  ],
  "ㄒㄧㄠ": [
    {
      "char": "小",
      "freq": 980
    },
    {
      "char": "笑",
      "freq": 970
    },
    {
      "char": "校",
      "freq": 960
    },
    {
      "char": "消",
      "freq": 950
    },
    {
      "char": "效",
      "freq": 940
    },
    {
      "char": "蕭",
      "freq": 930
    },
    {
      "char": "銷",
      "freq": 920
    }
  ],
  "ㄒㄧㄢ": [
    {
      "char": "先",
      "freq": 970
    },
    {
      "char": "現",
      "freq": 960
    },
    {
      "char": "線",
      "freq": 950
    },
    {
      "char": "仙",
      "freq": 940
    },
    {
      "char": "鮮",
      "freq": 930
    },
    {
      "char": "限",
      "freq": 920
    },
    {
      "char": "閒",
      "freq": 910
    },
    {
      "char": "險",
      "freq": 900
    },
    {
      "char": "顯",
      "freq": 890
    }
  ],
  "ㄒㄧㄣ": [
    {
      "char": "心",
      "freq": 970
    },
    {
      "char": "新",
      "freq": 960
    },
    {
      "char": "信",
      "freq": 950
    },
    {
      "char": "星",
      "freq": 940
    },
    {
      "char": "興",
      "freq": 930
    },
    {
      "char": "辛",
      "freq": 920
    },
    {
      "char": "薪",
      "freq": 910
    }
  ],
  "ㄒㄧㄤ": [
    {
      "char": "想",
      "freq": 970
    },
    {
      "char": "向",
      "freq": 960
    },
    {
      "char": "像",
      "freq": 950
    },
    {
      "char": "相",
      "freq": 940
    },
    {
      "char": "香",
      "freq": 930
    },
    {
      "char": "箱",
      "freq": 920
    },
    {
      "char": "鄉",
      "freq": 910
    },
    {
      "char": "享",
      "freq": 900
    },
    {
      "char": "響",
      "freq": 890
    }
  ],
  "ㄒㄧㄥ": [
    {
      "char": "行",
      "freq": 970
    },
    {
      "char": "星",
      "freq": 960
    },
    {
      "char": "性",
      "freq": 950
    },
    {
      "char": "形",
      "freq": 940
    },
    {
      "char": "型",
      "freq": 930
    },
    {
      "char": "興",
      "freq": 920
    },
    {
      "char": "姓",
      "freq": 910
    },
    {
      "char": "醒",
      "freq": 900
    }
  ],
  "ㄒㄩ": [
    {
      "char": "需",
      "freq": 960
    },
    {
      "char": "許",
      "freq": 950
    },
    {
      "char": "續",
      "freq": 940
    },
    {
      "char": "虛",
      "freq": 930
    },
    {
      "char": "序",
      "freq": 920
    },
    {
      "char": "緒",
      "freq": 910
    },
    {
      "char": "蓄",
      "freq": 900
    }
  ],
  "ㄒㄩㄝ": [
    {
      "char": "學",
      "freq": 970
    },
    {
      "char": "雪",
      "freq": 960
    },
    {
      "char": "血",
      "freq": 940
    },
    {
      "char": "穴",
      "freq": 920
    }
  ],
  "ㄒㄩㄢ": [
    {
      "char": "選",
      "freq": 960
    },
    {
      "char": "宣",
      "freq": 950
    },
    {
      "char": "旋",
      "freq": 940
    },
    {
      "char": "懸",
      "freq": 930
    },
    {
      "char": "玄",
      "freq": 920
    }
  ],
  "ㄒㄩㄣ": [
    {
      "char": "訓",
      "freq": 960
    },
    {
      "char": "尋",
      "freq": 950
    },
    {
      "char": "巡",
      "freq": 930
    },
    {
      "char": "迅",
      "freq": 920
    },
    {
      "char": "訊",
      "freq": 910
    }
  ],
  "ㄓ": [
    {
      "char": "之",
      "freq": 970
    },
    {
      "char": "知",
      "freq": 960
    },
    {
      "char": "只",
      "freq": 950
    },
    {
      "char": "支",
      "freq": 940
    },
    {
      "char": "值",
      "freq": 930
    },
    {
      "char": "織",
      "freq": 920
    },
    {
      "char": "指",
      "freq": 910
    },
    {
      "char": "止",
      "freq": 900
    }
  ],
  "ㄓㄚ": [
    {
      "char": "扎",
      "freq": 940
    },
    {
      "char": "炸",
      "freq": 930
    },
    {
      "char": "渣",
      "freq": 920
    },
    {
      "char": "榨",
      "freq": 910
    }
  ],
  "ㄓㄞ": [
    {
      "char": "摘",
      "freq": 940
    },
    {
      "char": "宅",
      "freq": 930
    },
    {
      "char": "窄",
      "freq": 920
    }
  ],
  "ㄓㄢ": [
    {
      "char": "站",
      "freq": 960
    },
    {
      "char": "戰",
      "freq": 950
    },
    {
      "char": "展",
      "freq": 940
    },
    {
      "char": "佔",
      "freq": 930
    },
    {
      "char": "沾",
      "freq": 920
    }
  ],
  "ㄓㄤ": [
    {
      "char": "張",
      "freq": 960
    },
    {
      "char": "長",
      "freq": 950
    },
    {
      "char": "章",
      "freq": 940
    },
    {
      "char": "掌",
      "freq": 930
    },
    {
      "char": "丈",
      "freq": 920
    },
    {
      "char": "帳",
      "freq": 910
    }
  ],
  "ㄓㄠ": [
    {
      "char": "找",
      "freq": 960
    },
    {
      "char": "照",
      "freq": 950
    },
    {
      "char": "招",
      "freq": 940
    },
    {
      "char": "趙",
      "freq": 930
    },
    {
      "char": "朝",
      "freq": 920
    }
  ],
  "ㄓㄜ": [
    {
      "char": "這",
      "freq": 990
    },
    {
      "char": "者",
      "freq": 970
    },
    {
      "char": "折",
      "freq": 950
    },
    {
      "char": "哲",
      "freq": 940
    },
    {
      "char": "遮",
      "freq": 930
    }
  ],
  "ㄓㄟ": [
    {
      "char": "這",
      "freq": 980
    }
  ],
  "ㄓㄣ": [
    {
      "char": "真",
      "freq": 970
    },
    {
      "char": "陣",
      "freq": 960
    },
    {
      "char": "鎮",
      "freq": 950
    },
    {
      "char": "珍",
      "freq": 940
    },
    {
      "char": "針",
      "freq": 930
    },
    {
      "char": "震",
      "freq": 920
    },
    {
      "char": "診",
      "freq": 910
    }
  ],
  "ㄓㄥ": [
    {
      "char": "正",
      "freq": 970
    },
    {
      "char": "整",
      "freq": 960
    },
    {
      "char": "政",
      "freq": 950
    },
    {
      "char": "鄭",
      "freq": 940
    },
    {
      "char": "爭",
      "freq": 930
    },
    {
      "char": "證",
      "freq": 920
    },
    {
      "char": "征",
      "freq": 910
    },
    {
      "char": "蒸",
      "freq": 900
    }
  ],
  "ㄓㄨ": [
    {
      "char": "主",
      "freq": 970
    },
    {
      "char": "住",
      "freq": 960
    },
    {
      "char": "注",
      "freq": 950
    },
    {
      "char": "助",
      "freq": 940
    },
    {
      "char": "竹",
      "freq": 930
    },
    {
      "char": "著",
      "freq": 920
    },
    {
      "char": "豬",
      "freq": 910
    },
    {
      "char": "祝",
      "freq": 900
    },
    {
      "char": "築",
      "freq": 890
    }
  ],
  "ㄓㄨㄚ": [
    {
      "char": "抓",
      "freq": 950
    },
    {
      "char": "爪",
      "freq": 930
    }
  ],
  "ㄓㄨㄞ": [
    {
      "char": "拽",
      "freq": 920
    }
  ],
  "ㄓㄨㄢ": [
    {
      "char": "轉",
      "freq": 960
    },
    {
      "char": "專",
      "freq": 950
    },
    {
      "char": "傳",
      "freq": 940
    },
    {
      "char": "磚",
      "freq": 930
    }
  ],
  "ㄓㄨㄤ": [
    {
      "char": "裝",
      "freq": 960
    },
    {
      "char": "莊",
      "freq": 950
    },
    {
      "char": "壯",
      "freq": 940
    },
    {
      "char": "撞",
      "freq": 930
    },
    {
      "char": "狀",
      "freq": 920
    }
  ],
  "ㄓㄨㄟ": [
    {
      "char": "追",
      "freq": 960
    },
    {
      "char": "嘴",
      "freq": 930
    }
  ],
  "ㄓㄨㄥ": [
    {
      "char": "中",
      "freq": 990
    },
    {
      "char": "種",
      "freq": 960
    },
    {
      "char": "重",
      "freq": 950
    },
    {
      "char": "終",
      "freq": 940
    },
    {
      "char": "鐘",
      "freq": 930
    },
    {
      "char": "眾",
      "freq": 920
    },
    {
      "char": "忠",
      "freq": 910
    }
  ],
  "ㄓㄨㄛ": [
    {
      "char": "桌",
      "freq": 960
    },
    {
      "char": "著",
      "freq": 940
    },
    {
      "char": "捉",
      "freq": 920
    },
    {
      "char": "卓",
      "freq": 910
    }
  ],
  "ㄔ": [
    {
      "char": "吃",
      "freq": 960
    },
    {
      "char": "尺",
      "freq": 940
    },
    {
      "char": "赤",
      "freq": 920
    },
    {
      "char": "遲",
      "freq": 910
    }
  ],
  "ㄔㄚ": [
    {
      "char": "茶",
      "freq": 960
    },
    {
      "char": "查",
      "freq": 950
    },
    {
      "char": "差",
      "freq": 940
    },
    {
      "char": "插",
      "freq": 930
    },
    {
      "char": "察",
      "freq": 920
    }
  ],
  "ㄔㄞ": [
    {
      "char": "拆",
      "freq": 940
    },
    {
      "char": "柴",
      "freq": 930
    }
  ],
  "ㄔㄢ": [
    {
      "char": "產",
      "freq": 960
    },
    {
      "char": "纏",
      "freq": 940
    },
    {
      "char": "禪",
      "freq": 920
    },
    {
      "char": "鏟",
      "freq": 910
    }
  ],
  "ㄔㄤ": [
    {
      "char": "常",
      "freq": 960
    },
    {
      "char": "長",
      "freq": 950
    },
    {
      "char": "唱",
      "freq": 940
    },
    {
      "char": "場",
      "freq": 930
    },
    {
      "char": "廠",
      "freq": 920
    },
    {
      "char": "嘗",
      "freq": 910
    }
  ],
  "ㄔㄠ": [
    {
      "char": "超",
      "freq": 960
    },
    {
      "char": "潮",
      "freq": 950
    },
    {
      "char": "吵",
      "freq": 940
    },
    {
      "char": "朝",
      "freq": 930
    },
    {
      "char": "抄",
      "freq": 920
    },
    {
      "char": "炒",
      "freq": 910
    }
  ],
  "ㄔㄜ": [
    {
      "char": "車",
      "freq": 970
    },
    {
      "char": "扯",
      "freq": 920
    },
    {
      "char": "撤",
      "freq": 910
    }
  ],
  "ㄔㄣ": [
    {
      "char": "陳",
      "freq": 960
    },
    {
      "char": "沉",
      "freq": 950
    },
    {
      "char": "趁",
      "freq": 940
    },
    {
      "char": "晨",
      "freq": 930
    },
    {
      "char": "襯",
      "freq": 920
    }
  ],
  "ㄔㄥ": [
    {
      "char": "成",
      "freq": 970
    },
    {
      "char": "城",
      "freq": 960
    },
    {
      "char": "承",
      "freq": 950
    },
    {
      "char": "稱",
      "freq": 940
    },
    {
      "char": "程",
      "freq": 930
    },
    {
      "char": "誠",
      "freq": 920
    },
    {
      "char": "秤",
      "freq": 910
    }
  ],
  "ㄔㄨ": [
    {
      "char": "出",
      "freq": 970
    },
    {
      "char": "初",
      "freq": 960
    },
    {
      "char": "處",
      "freq": 950
    },
    {
      "char": "除",
      "freq": 940
    },
    {
      "char": "楚",
      "freq": 930
    },
    {
      "char": "觸",
      "freq": 920
    },
    {
      "char": "儲",
      "freq": 910
    }
  ],
  "ㄔㄨㄢ": [
    {
      "char": "傳",
      "freq": 960
    },
    {
      "char": "船",
      "freq": 950
    },
    {
      "char": "穿",
      "freq": 940
    },
    {
      "char": "串",
      "freq": 930
    },
    {
      "char": "川",
      "freq": 920
    }
  ],
  "ㄔㄨㄤ": [
    {
      "char": "窗",
      "freq": 960
    },
    {
      "char": "床",
      "freq": 950
    },
    {
      "char": "創",
      "freq": 940
    },
    {
      "char": "闖",
      "freq": 930
    }
  ],
  "ㄔㄨㄟ": [
    {
      "char": "吹",
      "freq": 950
    },
    {
      "char": "垂",
      "freq": 930
    },
    {
      "char": "錘",
      "freq": 920
    }
  ],
  "ㄔㄨㄣ": [
    {
      "char": "春",
      "freq": 960
    },
    {
      "char": "純",
      "freq": 950
    },
    {
      "char": "唇",
      "freq": 930
    }
  ],
  "ㄔㄨㄥ": [
    {
      "char": "充",
      "freq": 960
    },
    {
      "char": "衝",
      "freq": 950
    },
    {
      "char": "蟲",
      "freq": 940
    },
    {
      "char": "崇",
      "freq": 930
    },
    {
      "char": "寵",
      "freq": 920
    }
  ],
  "ㄕ": [
    {
      "char": "是",
      "freq": 999
    },
    {
      "char": "事",
      "freq": 970
    },
    {
      "char": "十",
      "freq": 960
    },
    {
      "char": "時",
      "freq": 950
    },
    {
      "char": "師",
      "freq": 940
    },
    {
      "char": "詩",
      "freq": 930
    },
    {
      "char": "石",
      "freq": 920
    },
    {
      "char": "失",
      "freq": 910
    },
    {
      "char": "史",
      "freq": 900
    },
    {
      "char": "食",
      "freq": 890
    }
  ],
  "ㄕㄚ": [
    {
      "char": "沙",
      "freq": 960
    },
    {
      "char": "殺",
      "freq": 950
    },
    {
      "char": "紗",
      "freq": 930
    },
    {
      "char": "傻",
      "freq": 920
    }
  ],
  "ㄕㄞ": [
    {
      "char": "曬",
      "freq": 930
    }
  ],
  "ㄕㄢ": [
    {
      "char": "山",
      "freq": 960
    },
    {
      "char": "善",
      "freq": 950
    },
    {
      "char": "閃",
      "freq": 940
    },
    {
      "char": "扇",
      "freq": 930
    },
    {
      "char": "衫",
      "freq": 920
    }
  ],
  "ㄕㄤ": [
    {
      "char": "上",
      "freq": 990
    },
    {
      "char": "商",
      "freq": 960
    },
    {
      "char": "傷",
      "freq": 950
    },
    {
      "char": "賞",
      "freq": 940
    },
    {
      "char": "尚",
      "freq": 930
    }
  ],
  "ㄕㄠ": [
    {
      "char": "少",
      "freq": 960
    },
    {
      "char": "紹",
      "freq": 950
    },
    {
      "char": "燒",
      "freq": 940
    },
    {
      "char": "勺",
      "freq": 920
    },
    {
      "char": "哨",
      "freq": 910
    }
  ],
  "ㄕㄜ": [
    {
      "char": "設",
      "freq": 960
    },
    {
      "char": "社",
      "freq": 950
    },
    {
      "char": "射",
      "freq": 940
    },
    {
      "char": "蛇",
      "freq": 930
    },
    {
      "char": "捨",
      "freq": 920
    }
  ],
  "ㄕㄟ": [
    {
      "char": "誰",
      "freq": 960
    }
  ],
  "ㄕㄣ": [
    {
      "char": "身",
      "freq": 960
    },
    {
      "char": "深",
      "freq": 950
    },
    {
      "char": "神",
      "freq": 940
    },
    {
      "char": "甚",
      "freq": 930
    },
    {
      "char": "伸",
      "freq": 920
    },
    {
      "char": "審",
      "freq": 910
    },
    {
      "char": "慎",
      "freq": 900
    }
  ],
  "ㄕㄥ": [
    {
      "char": "生",
      "freq": 970
    },
    {
      "char": "聲",
      "freq": 960
    },
    {
      "char": "勝",
      "freq": 950
    },
    {
      "char": "省",
      "freq": 940
    },
    {
      "char": "升",
      "freq": 930
    },
    {
      "char": "剩",
      "freq": 920
    },
    {
      "char": "聖",
      "freq": 910
    }
  ],
  "ㄕㄨ": [
    {
      "char": "書",
      "freq": 960
    },
    {
      "char": "數",
      "freq": 950
    },
    {
      "char": "樹",
      "freq": 940
    },
    {
      "char": "束",
      "freq": 930
    },
    {
      "char": "屬",
      "freq": 920
    },
    {
      "char": "鼠",
      "freq": 910
    },
    {
      "char": "述",
      "freq": 900
    },
    {
      "char": "熟",
      "freq": 890
    },
    {
      "char": "術",
      "freq": 880
    }
  ],
  "ㄕㄨㄚ": [
    {
      "char": "刷",
      "freq": 940
    },
    {
      "char": "耍",
      "freq": 920
    }
  ],
  "ㄕㄨㄞ": [
    {
      "char": "帥",
      "freq": 940
    },
    {
      "char": "摔",
      "freq": 930
    },
    {
      "char": "甩",
      "freq": 920
    }
  ],
  "ㄕㄨㄢ": [
    {
      "char": "算",
      "freq": 950
    },
    {
      "char": "栓",
      "freq": 930
    }
  ],
  "ㄕㄨㄤ": [
    {
      "char": "雙",
      "freq": 960
    },
    {
      "char": "爽",
      "freq": 940
    },
    {
      "char": "霜",
      "freq": 930
    }
  ],
  "ㄕㄨㄟ": [
    {
      "char": "水",
      "freq": 970
    },
    {
      "char": "誰",
      "freq": 960
    },
    {
      "char": "睡",
      "freq": 950
    },
    {
      "char": "稅",
      "freq": 930
    }
  ],
  "ㄕㄨㄣ": [
    {
      "char": "順",
      "freq": 960
    }
  ],
  "ㄕㄨㄛ": [
    {
      "char": "說",
      "freq": 970
    },
    {
      "char": "碩",
      "freq": 930
    }
  ],
  "ㄖ": [
    {
      "char": "日",
      "freq": 960
    }
  ],
  "ㄖㄢ": [
    {
      "char": "然",
      "freq": 970
    },
    {
      "char": "染",
      "freq": 940
    },
    {
      "char": "燃",
      "freq": 930
    }
  ],
  "ㄖㄤ": [
    {
      "char": "讓",
      "freq": 960
    },
    {
      "char": "壤",
      "freq": 920
    }
  ],
  "ㄖㄠ": [
    {
      "char": "繞",
      "freq": 940
    },
    {
      "char": "擾",
      "freq": 930
    },
    {
      "char": "饒",
      "freq": 920
    }
  ],
  "ㄖㄜ": [
    {
      "char": "熱",
      "freq": 960
    },
    {
      "char": "惹",
      "freq": 930
    }
  ],
  "ㄖㄣ": [
    {
      "char": "人",
      "freq": 990
    },
    {
      "char": "認",
      "freq": 960
    },
    {
      "char": "任",
      "freq": 950
    },
    {
      "char": "忍",
      "freq": 940
    },
    {
      "char": "仁",
      "freq": 930
    },
    {
      "char": "刃",
      "freq": 920
    }
  ],
  "ㄖㄥ": [
    {
      "char": "仍",
      "freq": 950
    },
    {
      "char": "扔",
      "freq": 940
    }
  ],
  "ㄖㄨ": [
    {
      "char": "如",
      "freq": 960
    },
    {
      "char": "入",
      "freq": 950
    },
    {
      "char": "乳",
      "freq": 930
    }
  ],
  "ㄖㄨㄢ": [
    {
      "char": "軟",
      "freq": 960
    },
    {
      "char": "阮",
      "freq": 920
    }
  ],
  "ㄖㄨㄥ": [
    {
      "char": "容",
      "freq": 960
    },
    {
      "char": "融",
      "freq": 950
    },
    {
      "char": "榮",
      "freq": 940
    },
    {
      "char": "絨",
      "freq": 920
    }
  ],
  "ㄖㄨㄛ": [
    {
      "char": "若",
      "freq": 960
    },
    {
      "char": "弱",
      "freq": 940
    }
  ],
  "ㄗ": [
    {
      "char": "字",
      "freq": 960
    },
    {
      "char": "自",
      "freq": 950
    },
    {
      "char": "子",
      "freq": 940
    },
    {
      "char": "資",
      "freq": 930
    },
    {
      "char": "紫",
      "freq": 920
    },
    {
      "char": "姿",
      "freq": 910
    }
  ],
  "ㄗㄚ": [
    {
      "char": "雜",
      "freq": 950
    },
    {
      "char": "砸",
      "freq": 930
    }
  ],
  "ㄗㄞ": [
    {
      "char": "在",
      "freq": 990
    },
    {
      "char": "再",
      "freq": 980
    },
    {
      "char": "載",
      "freq": 940
    },
    {
      "char": "災",
      "freq": 930
    },
    {
      "char": "栽",
      "freq": 920
    }
  ],
  "ㄗㄢ": [
    {
      "char": "暫",
      "freq": 950
    },
    {
      "char": "贊",
      "freq": 940
    },
    {
      "char": "咱",
      "freq": 930
    }
  ],
  "ㄗㄤ": [
    {
      "char": "髒",
      "freq": 940
    },
    {
      "char": "藏",
      "freq": 930
    },
    {
      "char": "葬",
      "freq": 920
    }
  ],
  "ㄗㄠ": [
    {
      "char": "早",
      "freq": 960
    },
    {
      "char": "造",
      "freq": 950
    },
    {
      "char": "遭",
      "freq": 940
    },
    {
      "char": "澡",
      "freq": 930
    },
    {
      "char": "灶",
      "freq": 920
    },
    {
      "char": "糟",
      "freq": 910
    }
  ],
  "ㄗㄜ": [
    {
      "char": "則",
      "freq": 960
    },
    {
      "char": "責",
      "freq": 950
    },
    {
      "char": "擇",
      "freq": 940
    }
  ],
  "ㄗㄣ": [
    {
      "char": "怎",
      "freq": 960
    }
  ],
  "ㄗㄥ": [
    {
      "char": "增",
      "freq": 960
    },
    {
      "char": "曾",
      "freq": 950
    },
    {
      "char": "贈",
      "freq": 930
    }
  ],
  "ㄗㄨ": [
    {
      "char": "組",
      "freq": 960
    },
    {
      "char": "族",
      "freq": 950
    },
    {
      "char": "租",
      "freq": 940
    },
    {
      "char": "足",
      "freq": 930
    },
    {
      "char": "祖",
      "freq": 920
    },
    {
      "char": "阻",
      "freq": 910
    }
  ],
  "ㄗㄨㄟ": [
    {
      "char": "最",
      "freq": 970
    },
    {
      "char": "罪",
      "freq": 950
    },
    {
      "char": "嘴",
      "freq": 940
    },
    {
      "char": "醉",
      "freq": 930
    }
  ],
  "ㄗㄨㄢ": [
    {
      "char": "鑽",
      "freq": 940
    }
  ],
  "ㄗㄨㄥ": [
    {
      "char": "總",
      "freq": 960
    },
    {
      "char": "縱",
      "freq": 940
    },
    {
      "char": "宗",
      "freq": 930
    },
    {
      "char": "棕",
      "freq": 920
    }
  ],
  "ㄗㄨㄛ": [
    {
      "char": "做",
      "freq": 970
    },
    {
      "char": "作",
      "freq": 960
    },
    {
      "char": "坐",
      "freq": 950
    },
    {
      "char": "座",
      "freq": 940
    },
    {
      "char": "左",
      "freq": 930
    },
    {
      "char": "昨",
      "freq": 920
    }
  ],
  "ㄘ": [
    {
      "char": "次",
      "freq": 960
    },
    {
      "char": "此",
      "freq": 950
    },
    {
      "char": "刺",
      "freq": 930
    },
    {
      "char": "詞",
      "freq": 920
    }
  ],
  "ㄘㄚ": [
    {
      "char": "擦",
      "freq": 940
    }
  ],
  "ㄘㄞ": [
    {
      "char": "才",
      "freq": 960
    },
    {
      "char": "材",
      "freq": 950
    },
    {
      "char": "財",
      "freq": 940
    },
    {
      "char": "裁",
      "freq": 930
    },
    {
      "char": "採",
      "freq": 920
    },
    {
      "char": "菜",
      "freq": 910
    },
    {
      "char": "猜",
      "freq": 900
    }
  ],
  "ㄘㄢ": [
    {
      "char": "參",
      "freq": 960
    },
    {
      "char": "餐",
      "freq": 950
    },
    {
      "char": "殘",
      "freq": 940
    },
    {
      "char": "慚",
      "freq": 920
    }
  ],
  "ㄘㄤ": [
    {
      "char": "藏",
      "freq": 950
    },
    {
      "char": "蒼",
      "freq": 940
    },
    {
      "char": "倉",
      "freq": 930
    },
    {
      "char": "艙",
      "freq": 920
    }
  ],
  "ㄘㄠ": [
    {
      "char": "操",
      "freq": 960
    },
    {
      "char": "草",
      "freq": 950
    },
    {
      "char": "曹",
      "freq": 930
    }
  ],
  "ㄘㄜ": [
    {
      "char": "策",
      "freq": 960
    },
    {
      "char": "測",
      "freq": 950
    },
    {
      "char": "側",
      "freq": 940
    },
    {
      "char": "冊",
      "freq": 930
    }
  ],
  "ㄘㄥ": [
    {
      "char": "層",
      "freq": 960
    },
    {
      "char": "曾",
      "freq": 950
    },
    {
      "char": "蹭",
      "freq": 920
    }
  ],
  "ㄘㄨ": [
    {
      "char": "粗",
      "freq": 950
    },
    {
      "char": "促",
      "freq": 940
    },
    {
      "char": "醋",
      "freq": 930
    }
  ],
  "ㄘㄨㄟ": [
    {
      "char": "催",
      "freq": 950
    },
    {
      "char": "脆",
      "freq": 940
    }
  ],
  "ㄘㄨㄣ": [
    {
      "char": "村",
      "freq": 950
    },
    {
      "char": "存",
      "freq": 940
    },
    {
      "char": "寸",
      "freq": 930
    }
  ],
  "ㄘㄨㄥ": [
    {
      "char": "從",
      "freq": 960
    },
    {
      "char": "聰",
      "freq": 950
    },
    {
      "char": "蔥",
      "freq": 930
    }
  ],
  "ㄘㄨㄛ": [
    {
      "char": "錯",
      "freq": 960
    },
    {
      "char": "措",
      "freq": 940
    }
  ],
  "ㄙ": [
    {
      "char": "四",
      "freq": 960
    },
    {
      "char": "思",
      "freq": 950
    },
    {
      "char": "死",
      "freq": 940
    },
    {
      "char": "似",
      "freq": 930
    },
    {
      "char": "私",
      "freq": 920
    },
    {
      "char": "司",
      "freq": 910
    },
    {
      "char": "絲",
      "freq": 900
    }
  ],
  "ㄙㄚ": [
    {
      "char": "撒",
      "freq": 940
    },
    {
      "char": "灑",
      "freq": 920
    }
  ],
  "ㄙㄞ": [
    {
      "char": "賽",
      "freq": 950
    },
    {
      "char": "塞",
      "freq": 940
    }
  ],
  "ㄙㄢ": [
    {
      "char": "三",
      "freq": 970
    },
    {
      "char": "散",
      "freq": 950
    },
    {
      "char": "傘",
      "freq": 930
    }
  ],
  "ㄙㄤ": [
    {
      "char": "嗓",
      "freq": 930
    },
    {
      "char": "喪",
      "freq": 920
    },
    {
      "char": "桑",
      "freq": 910
    }
  ],
  "ㄙㄠ": [
    {
      "char": "掃",
      "freq": 950
    },
    {
      "char": "嫂",
      "freq": 920
    },
    {
      "char": "騷",
      "freq": 910
    }
  ],
  "ㄙㄜ": [
    {
      "char": "色",
      "freq": 960
    },
    {
      "char": "瑟",
      "freq": 920
    }
  ],
  "ㄙㄣ": [
    {
      "char": "森",
      "freq": 950
    }
  ],
  "ㄙㄥ": [
    {
      "char": "僧",
      "freq": 920
    }
  ],
  "ㄙㄨ": [
    {
      "char": "蘇",
      "freq": 950
    },
    {
      "char": "素",
      "freq": 940
    },
    {
      "char": "速",
      "freq": 930
    },
    {
      "char": "宿",
      "freq": 920
    },
    {
      "char": "塑",
      "freq": 910
    },
    {
      "char": "訴",
      "freq": 900
    },
    {
      "char": "酥",
      "freq": 890
    }
  ],
  "ㄙㄨㄟ": [
    {
      "char": "隨",
      "freq": 960
    },
    {
      "char": "歲",
      "freq": 950
    },
    {
      "char": "碎",
      "freq": 940
    },
    {
      "char": "雖",
      "freq": 930
    }
  ],
  "ㄙㄨㄢ": [
    {
      "char": "算",
      "freq": 960
    },
    {
      "char": "酸",
      "freq": 940
    },
    {
      "char": "蒜",
      "freq": 920
    }
  ],
  "ㄙㄨㄣ": [
    {
      "char": "孫",
      "freq": 960
    },
    {
      "char": "損",
      "freq": 940
    },
    {
      "char": "筍",
      "freq": 920
    }
  ],
  "ㄙㄨㄥ": [
    {
      "char": "送",
      "freq": 960
    },
    {
      "char": "松",
      "freq": 950
    },
    {
      "char": "宋",
      "freq": 940
    },
    {
      "char": "頌",
      "freq": 920
    },
    {
      "char": "誦",
      "freq": 910
    }
  ],
  "ㄙㄨㄛ": [
    {
      "char": "所",
      "freq": 970
    },
    {
      "char": "索",
      "freq": 950
    },
    {
      "char": "鎖",
      "freq": 940
    },
    {
      "char": "縮",
      "freq": 930
    }
  ],
  "ㄧ": [
    {
      "char": "一",
      "freq": 999
    },
    {
      "char": "已",
      "freq": 960
    },
    {
      "char": "以",
      "freq": 950
    },
    {
      "char": "意",
      "freq": 940
    },
    {
      "char": "衣",
      "freq": 930
    },
    {
      "char": "依",
      "freq": 920
    },
    {
      "char": "醫",
      "freq": 910
    },
    {
      "char": "億",
      "freq": 900
    }
  ],
  "ㄧㄚ": [
    {
      "char": "呀",
      "freq": 950
    },
    {
      "char": "壓",
      "freq": 940
    },
    {
      "char": "牙",
      "freq": 930
    },
    {
      "char": "鴨",
      "freq": 920
    }
  ],
  "ㄧㄝ": [
    {
      "char": "也",
      "freq": 980
    },
    {
      "char": "夜",
      "freq": 960
    },
    {
      "char": "業",
      "freq": 950
    },
    {
      "char": "葉",
      "freq": 940
    },
    {
      "char": "野",
      "freq": 930
    },
    {
      "char": "頁",
      "freq": 920
    }
  ],
  "ㄧㄠ": [
    {
      "char": "要",
      "freq": 980
    },
    {
      "char": "藥",
      "freq": 960
    },
    {
      "char": "搖",
      "freq": 940
    },
    {
      "char": "咬",
      "freq": 930
    },
    {
      "char": "腰",
      "freq": 920
    },
    {
      "char": "邀",
      "freq": 910
    }
  ],
  "ㄧㄡ": [
    {
      "char": "有",
      "freq": 990
    },
    {
      "char": "又",
      "freq": 970
    },
    {
      "char": "右",
      "freq": 960
    },
    {
      "char": "油",
      "freq": 950
    },
    {
      "char": "由",
      "freq": 940
    },
    {
      "char": "友",
      "freq": 930
    },
    {
      "char": "游",
      "freq": 920
    },
    {
      "char": "優",
      "freq": 910
    },
    {
      "char": "尤",
      "freq": 900
    }
  ],
  "ㄧㄢ": [
    {
      "char": "眼",
      "freq": 960
    },
    {
      "char": "言",
      "freq": 950
    },
    {
      "char": "煙",
      "freq": 940
    },
    {
      "char": "嚴",
      "freq": 930
    },
    {
      "char": "演",
      "freq": 920
    },
    {
      "char": "研",
      "freq": 910
    },
    {
      "char": "鹽",
      "freq": 900
    },
    {
      "char": "延",
      "freq": 890
    },
    {
      "char": "驗",
      "freq": 880
    }
  ],
  "ㄧㄣ": [
    {
      "char": "因",
      "freq": 960
    },
    {
      "char": "音",
      "freq": 950
    },
    {
      "char": "銀",
      "freq": 940
    },
    {
      "char": "引",
      "freq": 930
    },
    {
      "char": "飲",
      "freq": 920
    },
    {
      "char": "印",
      "freq": 910
    },
    {
      "char": "隱",
      "freq": 900
    }
  ],
  "ㄧㄤ": [
    {
      "char": "樣",
      "freq": 960
    },
    {
      "char": "養",
      "freq": 950
    },
    {
      "char": "洋",
      "freq": 940
    },
    {
      "char": "陽",
      "freq": 930
    },
    {
      "char": "央",
      "freq": 920
    },
    {
      "char": "楊",
      "freq": 910
    },
    {
      "char": "羊",
      "freq": 900
    }
  ],
  "ㄧㄥ": [
    {
      "char": "英",
      "freq": 960
    },
    {
      "char": "影",
      "freq": 950
    },
    {
      "char": "應",
      "freq": 940
    },
    {
      "char": "營",
      "freq": 930
    },
    {
      "char": "迎",
      "freq": 920
    },
    {
      "char": "嬰",
      "freq": 910
    },
    {
      "char": "鷹",
      "freq": 900
    }
  ],
  "ㄨ": [
    {
      "char": "五",
      "freq": 960
    },
    {
      "char": "武",
      "freq": 950
    },
    {
      "char": "物",
      "freq": 940
    },
    {
      "char": "舞",
      "freq": 930
    },
    {
      "char": "務",
      "freq": 920
    },
    {
      "char": "無",
      "freq": 910
    },
    {
      "char": "午",
      "freq": 900
    },
    {
      "char": "悟",
      "freq": 890
    }
  ],
  "ㄨㄚ": [
    {
      "char": "挖",
      "freq": 940
    },
    {
      "char": "蛙",
      "freq": 930
    },
    {
      "char": "娃",
      "freq": 920
    },
    {
      "char": "瓦",
      "freq": 910
    }
  ],
  "ㄨㄛ": [
    {
      "char": "我",
      "freq": 990
    },
    {
      "char": "握",
      "freq": 940
    },
    {
      "char": "臥",
      "freq": 930
    },
    {
      "char": "窩",
      "freq": 920
    }
  ],
  "ㄨㄞ": [
    {
      "char": "外",
      "freq": 970
    },
    {
      "char": "歪",
      "freq": 930
    }
  ],
  "ㄨㄟ": [
    {
      "char": "為",
      "freq": 980
    },
    {
      "char": "位",
      "freq": 960
    },
    {
      "char": "味",
      "freq": 950
    },
    {
      "char": "維",
      "freq": 940
    },
    {
      "char": "未",
      "freq": 930
    },
    {
      "char": "微",
      "freq": 920
    },
    {
      "char": "衛",
      "freq": 910
    },
    {
      "char": "危",
      "freq": 900
    },
    {
      "char": "圍",
      "freq": 890
    },
    {
      "char": "偉",
      "freq": 880
    }
  ],
  "ㄨㄢ": [
    {
      "char": "萬",
      "freq": 970
    },
    {
      "char": "完",
      "freq": 960
    },
    {
      "char": "晚",
      "freq": 950
    },
    {
      "char": "玩",
      "freq": 940
    },
    {
      "char": "碗",
      "freq": 930
    },
    {
      "char": "灣",
      "freq": 920
    },
    {
      "char": "彎",
      "freq": 910
    },
    {
      "char": "丸",
      "freq": 900
    }
  ],
  "ㄨㄣ": [
    {
      "char": "問",
      "freq": 960
    },
    {
      "char": "文",
      "freq": 950
    },
    {
      "char": "聞",
      "freq": 940
    },
    {
      "char": "溫",
      "freq": 930
    },
    {
      "char": "穩",
      "freq": 920
    },
    {
      "char": "吻",
      "freq": 910
    }
  ],
  "ㄨㄤ": [
    {
      "char": "王",
      "freq": 970
    },
    {
      "char": "往",
      "freq": 960
    },
    {
      "char": "望",
      "freq": 950
    },
    {
      "char": "忘",
      "freq": 940
    },
    {
      "char": "網",
      "freq": 930
    }
  ],
  "ㄨㄥ": [
    {
      "char": "翁",
      "freq": 930
    }
  ],
  "ㄩ": [
    {
      "char": "於",
      "freq": 960
    },
    {
      "char": "魚",
      "freq": 950
    },
    {
      "char": "雨",
      "freq": 940
    },
    {
      "char": "語",
      "freq": 930
    },
    {
      "char": "育",
      "freq": 920
    },
    {
      "char": "遇",
      "freq": 910
    },
    {
      "char": "御",
      "freq": 900
    },
    {
      "char": "宇",
      "freq": 890
    },
    {
      "char": "羽",
      "freq": 880
    }
  ],
  "ㄩㄝ": [
    {
      "char": "月",
      "freq": 960
    },
    {
      "char": "越",
      "freq": 950
    },
    {
      "char": "約",
      "freq": 940
    },
    {
      "char": "閱",
      "freq": 930
    },
    {
      "char": "樂",
      "freq": 920
    }
  ],
  "ㄩㄢ": [
    {
      "char": "原",
      "freq": 960
    },
    {
      "char": "園",
      "freq": 950
    },
    {
      "char": "遠",
      "freq": 940
    },
    {
      "char": "院",
      "freq": 930
    },
    {
      "char": "元",
      "freq": 920
    },
    {
      "char": "員",
      "freq": 910
    },
    {
      "char": "源",
      "freq": 900
    },
    {
      "char": "圓",
      "freq": 890
    },
    {
      "char": "願",
      "freq": 880
    }
  ],
  "ㄩㄣ": [
    {
      "char": "雲",
      "freq": 960
    },
    {
      "char": "運",
      "freq": 950
    },
    {
      "char": "允",
      "freq": 930
    },
    {
      "char": "暈",
      "freq": 920
    }
  ],
  "ㄩㄥ": [
    {
      "char": "用",
      "freq": 980
    },
    {
      "char": "勇",
      "freq": 960
    },
    {
      "char": "永",
      "freq": 950
    },
    {
      "char": "擁",
      "freq": 940
    },
    {
      "char": "庸",
      "freq": 920
    }
  ],
  "ㄦ": [
    {
      "char": "二",
      "freq": 960
    },
    {
      "char": "耳",
      "freq": 950
    },
    {
      "char": "兒",
      "freq": 940
    },
    {
      "char": "而",
      "freq": 930
    },
    {
      "char": "爾",
      "freq": 920
    }
  ],
  "ㄝ": [
    {
      "char": "耶",
      "freq": 930
    }
  ],
  "ㄅㄛ": [
    {
      "char": "波",
      "freq": 950
    },
    {
      "char": "播",
      "freq": 940
    },
    {
      "char": "博",
      "freq": 930
    },
    {
      "char": "伯",
      "freq": 920
    },
    {
      "char": "薄",
      "freq": 910
    }
  ],
  "ㄆㄛ": [
    {
      "char": "破",
      "freq": 960
    },
    {
      "char": "婆",
      "freq": 940
    },
    {
      "char": "潑",
      "freq": 930
    },
    {
      "char": "迫",
      "freq": 920
    },
    {
      "char": "坡",
      "freq": 910
    }
  ],
  "ㄌㄛ": [
    {
      "char": "囉",
      "freq": 920
    }
  ],
  "ㄉㄨㄛ": [
    {
      "char": "多",
      "freq": 970
    },
    {
      "char": "朵",
      "freq": 940
    },
    {
      "char": "躲",
      "freq": 930
    },
    {
      "char": "奪",
      "freq": 920
    }
  ],
  "ㄊㄨㄛ": [
    {
      "char": "脫",
      "freq": 950
    },
    {
      "char": "拖",
      "freq": 940
    },
    {
      "char": "托",
      "freq": 930
    },
    {
      "char": "妥",
      "freq": 920
    }
  ],
  "ㄋㄨㄛ": [
    {
      "char": "挪",
      "freq": 930
    },
    {
      "char": "諾",
      "freq": 920
    }
  ],
  "ㄌㄨㄛ": [
    {
      "char": "落",
      "freq": 960
    },
    {
      "char": "羅",
      "freq": 950
    },
    {
      "char": "洛",
      "freq": 940
    },
    {
      "char": "絡",
      "freq": 930
    },
    {
      "char": "裸",
      "freq": 920
    }
  ],
  "ㄎㄨㄛ": [
    {
      "char": "括",
      "freq": 940
    },
    {
      "char": "闊",
      "freq": 930
    },
    {
      "char": "擴",
      "freq": 920
    }
  ],
  "ㄔㄨㄛ": [
    {
      "char": "戳",
      "freq": 920
    }
  ],
  "ㄈㄡ": [
    {
      "char": "否",
      "freq": 950
    }
  ],
  "ㄉㄡ": [
    {
      "char": "都",
      "freq": 970
    },
    {
      "char": "斗",
      "freq": 950
    },
    {
      "char": "豆",
      "freq": 940
    },
    {
      "char": "逗",
      "freq": 930
    },
    {
      "char": "抖",
      "freq": 920
    }
  ],
  "ㄊㄡ": [
    {
      "char": "頭",
      "freq": 970
    },
    {
      "char": "透",
      "freq": 950
    },
    {
      "char": "偷",
      "freq": 940
    },
    {
      "char": "投",
      "freq": 930
    }
  ],
  "ㄋㄡ": [
    {
      "char": "扭",
      "freq": 930
    }
  ],
  "ㄌㄡ": [
    {
      "char": "樓",
      "freq": 960
    },
    {
      "char": "漏",
      "freq": 940
    },
    {
      "char": "摟",
      "freq": 920
    }
  ],
  "ㄍㄡ": [
    {
      "char": "夠",
      "freq": 960
    },
    {
      "char": "狗",
      "freq": 950
    },
    {
      "char": "構",
      "freq": 940
    },
    {
      "char": "溝",
      "freq": 930
    },
    {
      "char": "鉤",
      "freq": 920
    }
  ],
  "ㄏㄡ": [
    {
      "char": "後",
      "freq": 970
    },
    {
      "char": "厚",
      "freq": 960
    },
    {
      "char": "猴",
      "freq": 940
    },
    {
      "char": "喉",
      "freq": 930
    },
    {
      "char": "候",
      "freq": 920
    },
    {
      "char": "吼",
      "freq": 910
    }
  ],
  "ㄓㄡ": [
    {
      "char": "週",
      "freq": 960
    },
    {
      "char": "州",
      "freq": 950
    },
    {
      "char": "舟",
      "freq": 940
    },
    {
      "char": "粥",
      "freq": 920
    },
    {
      "char": "肘",
      "freq": 910
    }
  ],
  "ㄔㄡ": [
    {
      "char": "抽",
      "freq": 950
    },
    {
      "char": "愁",
      "freq": 940
    },
    {
      "char": "醜",
      "freq": 930
    },
    {
      "char": "仇",
      "freq": 920
    },
    {
      "char": "臭",
      "freq": 910
    }
  ],
  "ㄕㄡ": [
    {
      "char": "手",
      "freq": 970
    },
    {
      "char": "收",
      "freq": 960
    },
    {
      "char": "受",
      "freq": 950
    },
    {
      "char": "首",
      "freq": 940
    },
    {
      "char": "守",
      "freq": 930
    },
    {
      "char": "壽",
      "freq": 920
    },
    {
      "char": "瘦",
      "freq": 910
    }
  ],
  "ㄖㄡ": [
    {
      "char": "肉",
      "freq": 960
    },
    {
      "char": "柔",
      "freq": 940
    },
    {
      "char": "揉",
      "freq": 920
    }
  ],
  "ㄗㄡ": [
    {
      "char": "走",
      "freq": 960
    },
    {
      "char": "奏",
      "freq": 940
    }
  ],
  "ㄘㄡ": [
    {
      "char": "湊",
      "freq": 930
    }
  ],
  "ㄙㄡ": [
    {
      "char": "搜",
      "freq": 940
    },
    {
      "char": "艘",
      "freq": 920
    }
  ],
  "ㄆㄡ": [
    {
      "char": "剖",
      "freq": 930
    }
  ]
}